{"name": "七鱼资深大客户销售（杭州）-杭州研究院822", "link": "https://hr.163.com/position/detail.do?id=13953", "address": "杭州市", "cotegory": null, "type": "销售>销售", "num": "3人", "duty": ["（本岗位 杭州、上海、北京、广州、深圳均招人）", "1.负责产品目标行业大客户的销售工作，并达成销售目标；", "2.负责产品目标行业重点客户的客户开发、销售跟进、签单并回款等工作；", "3.负责行业标杆的树立，协助市场运营部门进行标杆客户案例的包装；", "4.负责行业的客户开发、行业需求的挖掘整理，行业竞品的信息收集，并向产品、运营等相关部门输出；", "5.整合公司内部外部资源，为内外部销售渠道提供大客户辅助销售支持；", "6.整理行业销售经验，向电销、区域销售、合作伙伴进行行业销售经验输出。"], "requir": ["1.本科以上学历，具有2年以上云计算产品软件产品或项目销售经验；", "2.有政府、汽车、电商、教育等行业客户资源及销售经验，及集成商、渠道资源；", "3.具备超强的需求挖掘和产品引导能力、方案及输出能力，良好的团队协作精神；", "4.非常强的大客户销售开发能力和顾问式销售能力，有优秀的的销售业绩；", "5.认同网易发展未来，热爱并充满信心；", "6.市场意识敏锐，学习能力强，资源整合协调能力，逻辑清晰，抗压并充满激情。"]},
{"name": "七鱼资深大客户销售（广州） - 杭州研究院822", "link": "https://hr.163.com/position/detail.do?id=15274", "address": "广州市", "cotegory": "杭州研究院", "type": "销售>销售", "num": "3人", "duty": ["（本岗位 杭州、上海、北京、广州、深圳均招人）", "1.负责产品目标行业大客户的销售工作，并达成销售目标；", "2.负责产品目标行业重点客户的客户开发、销售跟进、签单并回款等工作；", "3.负责行业标杆的树立，协助市场运营部门进行标杆客户案例的包装；", "4.负责行业的客户开发、行业需求的挖掘整理，行业竞品的信息收集，并向产品、运营等相关部门输出；", "5.整合公司内部外部资源，为内外部销售渠道提供大客户辅助销售支持；", "6.整理行业销售经验，向电销、区域销售、合作伙伴进行行业销售经验输出。"], "requir": ["1.本科以上学历，具有2年以上云计算产品软件产品或项目销售经验；", "2.有政府、汽车、电商、教育等行业客户资源及销售经验，及集成商、渠道资源；", "3.具备超强的需求挖掘和产品引导能力、方案及输出能力，良好的团队协作精神；", "4.非常强的大客户销售开发能力和顾问式销售能力，有优秀的的销售业绩；", "5.认同网易发展未来，热爱并充满信心；", "6.市场意识敏锐，学习能力强，资源整合协调能力，逻辑清晰，抗压并充满激情。"]},
{"name": "机器学习算法工程师（NLP） - 有道事业群704", "link": "https://hr.163.com/position/detail.do?id=20180", "address": "北京市", "cotegory": null, "type": "技术>人工智能", "num": "1人", "duty": ["1、对话系统的研发", "2、AI+教育方向的探索", "\t"], "requir": ["1、计算机相关专业，1-2年经验", "2、编程语言：Java/Python", "3、熟悉 NLP 相关技术，掌握机器学习通用算法", "4、有对话系统、问答系统研发经验，了解对话系统各方面", "5、（optional）教育类算法背景"]},
{"name": "引擎技术支持工程师 - 技术中心", "link": "https://hr.163.com/position/detail.do?id=20825", "address": "上海市", "cotegory": "互动娱乐事业群", "type": "技术>IT支持类", "num": "7人", "duty": ["工作职责：", "1.跟进公司自研引擎核心功能验证测试和发布", "2.负责设计和实现引擎自动化测试", "3.深入专项引擎研究，负责设计和开发引擎配套的测试插件/工具的开发", "4.建立各类针对性测试方案和游戏功能实现样例", "5.协助引擎开发组进行功能迭代和开发"], "requir": ["职位要求：", "1.本科及以上学历，至少3年工作经验，游戏行业相关优先考虑", "2. 有较强的编程能力，熟悉Python语言或其他至少一种脚本语言", "3. 有客户端开发或测试经验，对游戏引擎unity,unreal等有了解的优先考虑", "4.有游戏设计和实现经验，熟悉移动游戏性能定位的优先考虑", "5.善于沟通，有针对性设计方案或工具解决问题经验的优先考虑"]},
{"name": "七鱼资深大客户销售（北京）-杭州研究院822", "link": "https://hr.163.com/position/detail.do?id=13954", "address": "北京市", "cotegory": "杭州研究院", "type": "销售>销售", "num": "3人", "duty": ["（本岗位 杭州、上海、北京、广州、深圳均招人）", "1.负责产品目标行业大客户的销售工作，并达成销售目标；", "2.负责产品目标行业重点客户的客户开发、销售跟进、签单并回款等工作；", "3.负责行业标杆的树立，协助市场运营部门进行标杆客户案例的包装；", "4.负责行业的客户开发、行业需求的挖掘整理，行业竞品的信息收集，并向产品、运营等相关部门输出；", "5.整合公司内部外部资源，为内外部销售渠道提供大客户辅助销售支持；", "6.整理行业销售经验，向电销、区域销售、合作伙伴进行行业销售经验输出。"], "requir": ["1.本科以上学历，具有2年以上云计算产品软件产品或项目销售经验；", "2.有政府、汽车、电商、教育等行业客户资源及销售经验，及集成商、渠道资源；", "3.具备超强的需求挖掘和产品引导能力、方案及输出能力，良好的团队协作精神；", "4.非常强的大客户销售开发能力和顾问式销售能力，有优秀的的销售业绩；", "5.认同网易发展未来，热爱并充满信心；", "6.市场意识敏锐，学习能力强，资源整合协调能力，逻辑清晰，抗压并充满激情。"]},
{"name": "在线教育产品运营-K12方向", "link": "https://hr.163.com/position/detail.do?id=6408", "address": "北京市", "cotegory": null, "type": "产品>产品运营", "num": "1人", "duty": ["1、负责在线教育相关产品的运营工作，基于课程产品的内容运营，准确识别并深刻理解用户需求，具备敏锐的用户感觉； ", "2、负责有道精品课课程及APP平台的维护、运营，确保课程产品的品质，提升教育服务水平； ", "3、能对教育类产品进行分析，了解数据，并以此为依据推进课程产品改进 ； ", "4、对用户群体进行有序组织和内容管理，增加用户粘性、用户贡献和用户忠诚度，有针对性地策划用户活动，增加用户积极性和参与度；擅长qq运营者优先。 ", "5、定期收集、整理运营数据并收集使用产品过程中的问题及反馈，对运营数据进行统计与分析，形成对产品运营和设计有价值的文档，根据数据提出有效的应对策略和产品需求分析。"], "requir": ["1、统招全日制本科及以上学历，理科专业优先，并具备一定文字功底；", "2、工作主动，有良好的沟通协调能力以及团队合作精神； ", "3、热爱互联网，对教育行业有一定认识，善于把握用户各层次需求；并整合用户碎片化需求。 ", "4、有较强的洞察力和创新能力，有一定的敏感性； ", "5、具备良好的语言及文字表达能力，跨团队协作能力； ", "6、勤劳肯干，能够承担较大的工作压力，执行力强。"]},
{"name": "高级产品经理 - 有道事业群703", "link": "https://hr.163.com/position/detail.do?id=20828", "address": "北京市", "cotegory": null, "type": "产品>产品综合", "num": "1人", "duty": ["1、负责有道智能硬件中学习工具类产品的规划；", "2、持续监控行业、用户、竞品、销售变化，迭代式创新，优化产品线构成及产品能力；", "3、根据产品规划，确定切实可行的产品落地策略，积极推动产品内外部合作；", "4、负责团队内的资源协调及沟通管理，确保项目的高质量实施与落地；", "5、建立产品数据监控体系，分析产品数据变化原因及趋势，优化产品策略。"], "requir": ["1、3年以上产品策划经验，具有从0-1的产品搭建及后续运营迭代经验；", "2、结果导向，具有极强的产品落地能力；", "3、极强的学习能力与创新力、热爱生活、具有教育理想；", "4、有教育类、工具类产品设计经验优先。"]},
{"name": "在线教育辅导管理 - 有道事业群701", "link": "https://hr.163.com/position/detail.do?id=19354", "address": "北京市", "cotegory": "有道事业群", "type": "教育>教育", "num": "1人", "duty": ["1. 带领辅导老师执行各学科的服务方案及续报方案 ", "2. 及时反馈辅导老师团队工作中的各种问题，定时复盘  ", "3. 对辅导老师的工作进行及时纠偏 ", "4. 协调团队内部及与各个端口之间的工作 ", "5. 定期对团队辅导老师进行培训"], "requir": ["1. 本科以上学历，有在线辅导老师管理工作经验 ", "2. 英语专业优先 ", "3. 有服务意识，执行力强 "]},
{"name": "智能广告优化助理 - 有道事业群706", "link": "https://hr.163.com/position/detail.do?id=20826", "address": "广州市", "cotegory": null, "type": "市场>市场综合", "num": "1人", "duty": ["1，负责解决VIP客户的基本需求；", "2，按需求分析整理广告投放数据；", "3，广告图片的修改调整；", "4，上传客户广告；", "5，其他基础工作；"], "requir": ["1，具备较好的数据分析处理的能力，熟练使用excel；", "2，会使用PS软件；", "3，具备广告思维；注重细节，逻辑性强，善于沟通。"]},
{"name": "资深Java开发工程师（音街） - 音乐事业部002", "link": "https://hr.163.com/position/detail.do?id=20469", "address": "杭州市", "cotegory": "音乐事业部", "type": "技术>服务端开发", "num": "10人", "duty": ["网易云音乐创新业务服务端团队，服务于音街业务，同时支持云音乐基础平台、业务中台等建设。我们保持将最新技术引入提升开发效率，带给用户更好的体验 ", "1、根据产品需求完成模块设计、编码、测试以及文档编写等工作；", "2、负责后端系统的架构设计、开发和维护，系统具有可扩展性，并能够支持大量并发用户；  ", "3、持续优化系统性能，保证线上服务的高可用及稳定性。"], "requir": ["1、计算机相关专业，本科及以上学历； ", "2、3年以上java开发经验；", "3、熟练掌握MySQL、Redis中的一种或多种，能够进行使用优化；  ", "4、熟悉互联网中间件，如Kafka、RocketMQ、ZooKeeper等；", "5、有较好的学习与沟通能力，有创新力和责任感；", "6、高并发或者高可用等相关的架构设计经验者优先考虑；"]},
{"name": "网易有道精品课社群运营 - 有道事业群701", "link": "https://hr.163.com/position/detail.do?id=19932", "address": "武汉市", "cotegory": null, "type": "产品>产品运营", "num": "3人", "duty": ["【工作内容】", "1. 通过优化迭代课程服务流程提升用户学习效果；", "2. 通过用户调研、用户访谈等方式优化付费产品课程出勤率、课后作业完成率、课后作业正确率、阶段测评通过率等，以达到用户服务满意度指标；", "3. 配合课程进度，带领实习生和兼职一起完成付费课各项服务动作；", "4. 帮助用户处理课程相关问题（包含简单的学术型答疑），保证付费课服务期间的用户反馈渠道畅通。"], "requir": ["【任职要求】", "1.本科学历及以上；", "2.有教育行业相关工作经验，可放宽考虑；", "3.具有服务精神和较强的逻辑思维能力；", "4.良好的沟通能力、语言表达能力及团队协作能力。", "5.英语相关专业优先。"]},
{"name": "市场营销实习生（商务拓展） ", "link": "https://hr.163.com/position/detail.do?id=20821", "address": "杭州市", "cotegory": "音乐事业部", "type": "市场>市场综合", "num": "2人", "duty": ["1. 负责对接合作方APP、硬件、运营商等的接洽与商谈工作；", "2. 协助开展网易云音乐各种营销活动，包括活动策划与执行、数据处理，以及对外沟通；", "3. 协同多部门合作，有效整合各方资源。"], "requir": ["1. 2021年及之后毕业，大三/研一/研二的同学优先；", "2. 可稳定实习6个月，每周到岗4天以上；", "3. 商务谈判、沟通协调能力佳，有过活动组织策划、外联谈判经验者优先；", "4. 具有团队合作精神，性格开朗外向，责任心强，有工作热情。"]},
{"name": "逻辑英语产品运营 - 有道事业群701", "link": "https://hr.163.com/position/detail.do?id=20165", "address": "北京市", "cotegory": null, "type": "产品>产品运营", "num": "1人", "duty": ["1. 通过优化运营流程，设计营销漏斗，并不断优化效果，以达到最终业绩收入指标；", "2. 通过竞品调研、用户访谈和调研，体验课程打磨等运营动作，提升出勤率、转化率；", "3. 课程设计、外化、文案撰写等课程运营相关工作；", "4. 体验课社群运营优化，课程排课优化等关系到转化效率的工作。"], "requir": ["1. 本科学历及以上；", "2. 应届毕业生或有1-2年教育行业相关工作经验，并具备成功实施落地项目经验 ；", "3. 对数据敏感，有独立完整的数据分析经验，能快速发掘业务和数据的联系；", "4. 良好的沟通能力、语言表达能力及团队协作能力。"]},
{"name": "增长团队技术负责人 - 有道事业群701", "link": "https://hr.163.com/position/detail.do?id=20253", "address": "北京市", "cotegory": "有道事业群", "type": "技术>项目管理", "num": "1人", "duty": ["1、负责和产品、运营团队对接需求，推进相应的研发工作", "2、负责增长团队相关技术", "3、负责增长团队的研发管理"], "requir": ["1、计算机相关专业、良好的数据结构和算法基础，优秀的编码能力", "2、熟悉 Java/C++/Python/JavaScript/Go 语言中的一种", "3､ 有一线增长项目经验，强的学习能力", "4､ 具备良好技术、产品、商业视野，熟悉增长玩法，洞察技术行业趋势", "5、较强综合能力，有过前后端全栈开发经验的优先"]},
{"name": "在线教育用户运营-有道事业部096", "link": "https://hr.163.com/position/detail.do?id=13723", "address": "北京市", "cotegory": null, "type": "产品>产品运营", "num": "5人", "duty": ["1、负责高中学科用户运营，根据用户需求节点及产品运营节奏，策划并落实用户运营方案", "2、通过用户运营动作完成拉新指标，并提升用户粘性，实现意向价值用转化，为最终运营效果负责。", "3、熟悉QQ,微信等主流营销工具，善于学习互联网新型的营销知识，并能实操运营到实际工作中。"], "requir": ["1、有策划或参与过完整周期性用户生命周期的用户运营经验。", "2、抗压能力强，责任心强，良好的沟通力和团队协作精神； ", "3、 具备用户思维，喜欢和用户交流，逻辑条理清晰，较强的数据统计及分析的能力", "4、具备一定的文案功底和策划能力；"]},
{"name": "在线教育高级项目经理 - 有道精品课产品部006", "link": "https://hr.163.com/position/detail.do?id=18906", "address": "北京市", "cotegory": null, "type": "市场>市场综合", "num": "1人", "duty": ["1．结合公司发展战略，全面推进所属领域项目课程和服务体系建设，推动项目发展，制定产品发展战略规划。", "2．负责优秀的老师BD和优质内容的搭建工作，完善产品体系，打造出受学生欢迎的课程产品。", "3．构建教学教研管理体系，完成授课流程及配套服务的标准化建设，全面监控教学质量。", "4．收集各方数据，定期进行市场分析、竞品分析和用户研究，分析产品情况，持续优化产品体系。", "5．与协作部门紧密沟通共同推进产品市场变现和品牌影响力。"], "requir": ["1．本科（含）以上学历；", "2．对教育培训行业有深入了解；熟悉知识付费领域发展趋势和特点，有敏锐的市场洞察力和分析能力； ", "3．5年以上教育类产品研发、培训、管理经验，有成功的项目经验者优先考虑；", "4．热爱教育行业，具有创新开拓精神、责任心强，办事效率高；", "5．具有强组织协调、强沟通能力，先进的管理意识和能力。"]},
{"name": "在线教育数据运营分析 - 有道事业群701", "link": "https://hr.163.com/position/detail.do?id=19969", "address": "北京市", "cotegory": null, "type": "产品>产品运营", "num": "1人", "duty": ["职位描述", "1、负责K12业务运营相关数据进行收集和整理，构建业务数据指标体系；", "2、建立日常监控体系并维护监测数据报表，及时更新并长期监控；", "3、负责对于重点数据的深入挖掘分析，能够从分析中发现问题并为业务提供方向建议；", "4、提供可视化数据产出或查询工具（sql或报表），供项目组自行查询，提高运营效率；", "5、会同时兼带一些小型项目，参与到业务中，通过熟悉业务对数据分析逻辑和对业务建议更有针对性。"], "requir": ["任职要求：", "1、本科及以上学历，统计学、数学、计算机、信息管理相关专业优先； 熟练使用sql和excel及其他分析工具；", "2、2年以上互联网行业数据运营、数据分析经验；", "3、对数据敏感，对于精细化运营实践有自己的理解，掌握数据可视化和基本统计方法；", "4、具备良好的逻辑思考、业务理解和沟通表达能力，能够站在业务视角审视、发现并快速解决问题。"]},
{"name": "课程产品经理 - 有道事业群701", "link": "https://hr.163.com/position/detail.do?id=20145", "address": "北京市", "cotegory": "有道事业群", "type": "产品>产品策划", "num": "2人", "duty": ["1. 通过产品体验、用户调研、行业调研进行课程产品迭代改进，提升用户学习效果和学习体验。", "2. 参与有道精品课逻辑英语/全民英语背诵营课程迭代改进、服务迭代改进、产品功能研发等工作。", "3. 坚持从用户学习效果和用户学习体验出发，持续完善学习体验，服务体验。", "4. 与产品运营和售前协作，定位精准目标用户进行产品亮点外化，从产品设计满足目标用户需求角度给予支持，协助招生。"], "requir": ["1. 具有产品思维： 能够基于目标不断思考更优的解决方案。有能力独立分析梳理用户需求，聚焦重点，逻辑清晰。", "2. 熟悉英语学习过程&教学过程：熟悉英语语言学习过程，熟悉学习场景，深度接触过该类用户。", "3. 数据感： 数据分析能力，数据洞察能力是加分项，做产品的基本功需要学会基于数据做分析和迭代。", "4. 具有良好的沟通协作能力和服务精神。", "5. 同时就有产品经理工作经验和英文教学经验者优先。"]},
{"name": "K12语文学科运营 - 有道事业群701", "link": "https://hr.163.com/position/detail.do?id=20462", "address": "北京市", "cotegory": null, "type": "产品>产品运营", "num": "1人", "duty": ["1、与授课教师团队协作，设计初中在线课程产品，跟进课程方案设计和执行；", "2、为完善课程产品，进行用户调研、数据分析、教学质检反馈等，持续优化产品；", "3、围绕用户运营、活动运营、营销推广等手段，促进课程售卖；", "4、课程产品运营的相关其他工作，如向客服同事提供课程产品方面的信息协助等。"], "requir": ["岗位需求：", "1、统招全日制本科及以上学历，需要有在线教育语文学科工作经验，全职工作3年以上；", "2、熟悉初中高中培训市场，善于把握整合用户需求，有教学产品设计经验尤佳；", "3、具备良好的语言文字表达能力，沟通能力，跨团队协作能力；", "4、有较强的洞察力和创新能力，具备课程产品敏感性；", "5、能够承担较大的工作压力，执行力强，责任感强，有团队精神。"]},
{"name": "网易有道增长产品经理 - 有道事业部096", "link": "https://hr.163.com/position/detail.do?id=14976", "address": "北京市", "cotegory": "有道事业群", "type": "产品>产品策划", "num": "1人", "duty": ["1、以增长为目标，规划和设计产品，完成用户获取、用户裂变、用户转化漏斗优化等，最终找到可靠的新用户量高效增长路径", "2、充分理解教学产品，联动具体业务团队产生爆款内容，打造爆款营销方案", "3、研究和完善用户增长相关的数据探索，能够把握关键指标，关注转化数据，在各个转化环节上做优化"], "requir": ["1、极强的逻辑思维能力、良好的沟通协调、项目推动能力；", "2、具有2-5年用户增长经验，有实际的增长案例与成绩；", "3、理工科背景优先；", "4、热爱在线教育行业，相信在线教育未来。"]},
{"name": "大数据开发工程师微专业运营实习生-云课堂-有道事业群702 - 有道事业群702", "link": "https://hr.163.com/position/detail.do?id=20823", "address": "杭州市", "cotegory": null, "type": "产品>产品运营", "num": "1人", "duty": ["岗位描述：", "1、协助讲师PPT审核修改，PPT处理需要达到微专业红线标准，并具备良好的审美设计；", "2、协助讲师工程文件导出视频，对视频格式及内容进行初步审查，提供剪辑要点；", "3、协助讲师生产计划跟进，确保内容产出如期完成；", "4、负责大学计算机体系课程的上线和运营，制定营销策略，做好用户拉新、留存；"], "requir": ["岗位要求：", "1、计算机类相关专业，有教育行业背景的优先，善于沟通协调，责任心强，有较强的的逻辑思维和数据分析能力", "2、精通PPT制作技巧，具有较好的审美水平，熟悉视频工具的使用，有视频处理经验的优先；", "3、热爱互联网，参加过多个平台的线上课程，对线上教育平台有深刻认识。", "4、至少保证6个月实习时间，一周3天以上；", "5、勤劳肯干，能承担较大工作压力；"]},
{"name": "技术美术TA-合作产品部", "link": "https://hr.163.com/position/detail.do?id=13664", "address": "广州市", "cotegory": null, "type": "美术>游戏美术类", "num": "1人", "duty": ["1. 研究游戏项目中美术内容制作的各项工具使用。", "2. 熟悉并研究游戏引擎的各项功能使用。", "3. 充分了解美术各环节开发中的需求和问题，提供足够的技术支持。", "4. 为创建和优化美术资源开发的流程和规范提供技术性支持。", "5. 为达到更好的游戏美术效果，及时的做出有效的技术研究工作。", "6. 根据项目开发中策划、美术和程序的变化，不断性维护游戏美术内容开发流程、规范，以及引擎工具的使用。"], "requir": ["1. 有较好的美术专业能力，有较高的审美能力，精通于游戏美术各类资源开发的流程和规范。", "2. 对策划及程序的工作方式有足够的了解，能较好地与策划和程序进行项目协同开发，协助解决美术和程序间的技术问题。", "3. 能够与团队中各部门职员保持较好的沟通协作状态，有较好的逻辑思维能力，善于管理与自我管理，有较强的自主能动力。", "4. 精通3D美术内容制作工具，包括：3DSMax、Maya、Zbrush、XSI、Photoshop等。", "5. 精通至少一种主流游戏开发引擎,如：UnrealEngine、CryEngine、Unity3D等。", "6. 熟悉至少一种编程/脚本语言，如：MaxScript、UnrealScript、Mel、C++、C#等。", "7. 至少5年以上的游戏开发经验，2年以上技术美术相关经验。具备大型次世代游戏项目开发经验者优先。"]},
{"name": "资深嵌入式软件工程师 - 有道事业部036", "link": "https://hr.163.com/position/detail.do?id=17008", "address": "北京市", "cotegory": null, "type": "技术>技术综合", "num": "1人", "duty": ["1、完成嵌入式linux系统及服务器linux系统上的应用软件开发；", "2、按照产品需求完成软件设计,进行linux上的应用及驱动软件开发；", "3、按照软件设计逻辑，完成软件功能模块测试代码的设计和自动化测试； ", "4、维护和升级现有软件产品，快速定位并修复现有软件缺陷；", "5、学习开源软件代码，移植到软件产品中，同时维护公司对外的开源代码。"], "requir": ["1、精通C/C++/GO开发语言，具备linux应用程序开发经验，具备linux下驱动开发经验者优先，具备服务器开发经验者优先；", "2、熟练使用开源软件库，例如：QT、libcurl、openssl、boost库等； ", "3、熟悉QT、熟悉TCP/IP、UDP协议，具有基于socket网络通讯编程经验； ", "4、熟悉多线程、多进程的概念和编程；", "5、熟练使用git版本管理，具有良好的代码版本管理习惯；", "6、能够快速学习和善于从网络寻找学习资源；", "7、良好的团队合作精神。"]},
{"name": "产品经理实习生（杭州）-有道数学项目组", "link": "https://hr.163.com/position/detail.do?id=20776", "address": "杭州市", "cotegory": null, "type": "产品>产品综合", "num": "1人", "duty": ["职位描述", "1. 参与网易有道在线教育产品的产品工作。协助产品经理完成需求收集，数据分析，竞品调研等各类产品日常工作。", "2. 进行用户反馈收集，负责产品、运营相关问题的跟进处理，并能从中抽象出有价值的共性需求，推进功能化落地。", "3. 完成需求原型输出，PRD文档撰写。"], "requir": ["职位要求", "1. 全日制普通高校本科及以上学历在校生。", "2. 对产品经理工作内容有一定了解，有过产品经理实习经验者优先。", "3. 具备优秀的沟通表达能力，能很好的跟产品、运营、技术团队进行日常工作交流，保证各项工作顺利推进。", "4. 具备独立思考能力，愿意尝试和挑战新事物，有责任心。", "5. 能保证3个月以上实习时间，每周至少4天。"]},
{"name": "资深内控合规-杭州-网易严选", "link": "https://hr.163.com/position/detail.do?id=10753", "address": "杭州市", "cotegory": "严选事业部", "type": "电商>电商综合", "num": "1人", "duty": ["1.协助部门负责人搭建内控与风险管理体系的建设与运作，开展公司内控状况的评估诊断、风险识别及问题改进跟踪、内控体系建设及优化、风险评估等；", "2.负责建立及优化流程管理体系,推动流程管理体系在公司内部的有效运作;", "3.关注效率与风险的平衡，负责相关内控范围涉日常经营的内部控制，包含对日常业务中的重要风险做监测、识别、评估和改进，及时向管理层和业务部门反馈，输出高质量风险评估报告、改进建议报告等；", "4.日常负责与BU及其他部门密切合作，促进BU提升风险管理意识，优化内控政策、指引和流程，确保各项内控措施能高效、正确的执行;", "5.流程管理体系、方法的推广及培训，营造内控氛围"], "requir": ["1. 5年以上大型企业/上市公司风险管理、内部控制、流程管理、流程项目实施等相关工作经验，电商企业、内控咨询公司经验者优先；", "2. 具有丰富的风险管理工作经验，掌握风险评估诊断、风险识别、分析、研判等技能；", "3. 具备项目管理经验、BPM\\BPR流程管理、流程标准化等相关知识经验者优先；", "4. 优秀的沟通协调能力,具备协调解决跨部门问题的能力；良好的逻辑与控制能力，能够高效的完成工作任务;", "5. 具备优秀的职业素养与品德操守，责任心强，能承受较大工作压力，具备快速学习、理解业务的能力；", "6. 具备核心业务资格证书或CIA、CPA、CERM优先。"]},
{"name": "高级/资深概念设计师 - 用户体验中心", "link": "https://hr.163.com/position/detail.do?id=20779", "address": "广州市", "cotegory": "互动娱乐事业群", "type": "美术>游戏美术类", "num": "6人", "duty": ["1. 按游戏世界观设计场景应用概念设计", "2. 按世界观制定游戏场景UI分镜", "3. 根据分镜场景，设计UI场景三视图", "4. 按游戏世界观设计高要去大型原画icon", "5. 设计界面场景道具，应用道具类", "6. 游戏LOGO品牌类型涉及，VI设计相关"], "requir": ["1. 具有丰富的创新思维，积极主动把产品的要求做到专业水平，有较强的审美观念", "2. 具有扎实的美术功底，数位板绘画经验丰富，具备专业的平面设计和概念设定能力", "3. 能驾驭多种画风", "4. 熟练运用各种设计软件", "5. 有一至两年以上影视分镜、游戏开发、游戏设定或广告平面设计工作经验优先"]},
{"name": "资深java开发工程师 - 杭州研究院043", "link": "https://hr.163.com/position/detail.do?id=20822", "address": "杭州市", "cotegory": "杭州研究院", "type": "技术>服务端开发", "num": "1人", "duty": ["岗位职责：", "1、负责网易最大存储产品的业务和核心架构持续优化，包含：包括微服务化架构改造、全面CICD建设；", "2、负责对系统的持续优化，满足高可用、高性能、高扩展性、弹性等需求；"], "requir": ["任职要求：", "1、正直诚信、沉稳冷静、有责任感及良好的沟通能力；", "2、扎实的数据结构和算法基础，熟悉常用的设计模式；", "3、熟练掌握Java开发工具栈，熟悉常用的开发框架spring/springcloud、MyBatis等，熟悉Java JVM运行机制和性能调优者优先；", "4、熟练使用常用的数据库及中间件，包括MySQL、Redis、MQ、kafka、Elasticsearch（至少其中2项）；", "5、掌握Linux基础网络协议（TCP、UDP等），熟练使用Golang、C++编程的优先；", "6、熟练使用git、gerrit等代码管理工具，有良好的代码质量和工程质量意识，可配合测试人员设计并执行单元测试、集成测测试、异常测试；", "7、掌握至少一门脚本语言，如Python、Shell、Ruby等；", "8、熟悉swift、ceph rgw等开源对象存储项目者优先；", "9、熟悉容器化、微服务开发模式者优先。"]},
{"name": "资深绩效管理HR/绩效管理专家 - 人力资源部001", "link": "https://hr.163.com/position/detail.do?id=20607", "address": "杭州市", "cotegory": "人力资源部", "type": "职能>人力资源", "num": "1人", "duty": ["1、负责不断优化集团绩效管理政策，助力各业务单元绩效管理工作的有效开展；", "2、帮助各BU迭代和完善绩效管理工作，有效落地绩效管理PDCA的循环；", "3、将绩效管理的先进理念及措施有效进行产品需求转化，配合EHR团队进行绩效管理系统的功能迭代升级；", "4、负责进行公司层面绩效管理的赋能、宣贯及绩效文化的宣导；", "5、建立绩效管理相数据分析机制，不断进行绩效管理相关诊断，为人力资源管理工作提供优化建议；", "6、与其他HR模块联动，不断优化公司在人才、组织、文化方面的管理工作 。"], "requir": ["1、本科以上学历，5-10年工作经验，至少3年以上互联网或大型高新企业绩效管理工作经验，具有咨询公司和企业绩效实践双重背景者优先；", "2、熟悉各类绩效管理的工具及方法，有丰富的业务部门薪酬绩效方案设计及落地经验，对OKR绩效管理工具有深入学习和实践经验； ", "3、数据敏感度高，数据分析能力强，有体系化的思考力，能抓住核心，善于系统性解决问题； ", "4、懂人性，善沟通，有匠心；"]},
{"name": "商品设计师-杭州-网易严选", "link": "https://hr.163.com/position/detail.do?id=20547", "address": "杭州市", "cotegory": null, "type": "设计>商品设计", "num": "1人", "duty": ["1.负责严选商品设计、包装设计（居家生活类方向）", "2.能够独立完成从概念设计到3D效果图输出，有一定手绘基础", "3.结合竞品和行业趋势参与设计研究"], "requir": ["面向人群：海内外院校2021、2022届毕业生", "1.熟练掌握PS、AI、C4D等设计软件", "2.对造型、色彩、工艺、表面处理有基本的认知，熟悉包装材质工艺", "3.具备良好的审美和创造力，热爱生活，乐于研究、分析零售行业创新品牌和产品"]},
{"name": "创意视觉设计师-杭州-网易严选", "link": "https://hr.163.com/position/detail.do?id=20546", "address": "杭州市", "cotegory": null, "type": "设计>视觉设计", "num": "1人", "duty": ["1.通过不同形式的创意设计表达，完成品牌或商品相关的广告设计", "2.能够针对明确的主题进行图案设计，完成图案拓展"], "requir": ["面向人群：海内外院校2021、2022届毕业生", "1.具备良好的美学素养和排版能力，熟练运用PS\\AI等平面类设计软件", "2.热爱生活，有脑洞，能驾驭多种设计风格"]},
{"name": "大客户销售经理-广州-网易严选", "link": "https://hr.163.com/position/detail.do?id=14145", "address": "广州市", "cotegory": "严选事业部", "type": "销售>销售", "num": "1人", "duty": ["1、负责严选产品在集团客户和潜在大客户的开发、拓展、维护、销售工作", "2、负责2B行业客户的沟通、谈判、签约及回访、维护工作", "3、不断挖掘客户潜在价值，促成多场景合作，包括不限于积分兑换、营销礼赠、员工福利等。以达成客户与公司间最大价值的合作方式", "4、5年以上工作经验，2年以上2B企业行业背景", "5、有成熟的ToB企业销售成功经验或是项目经验"], "requir": ["1、5年以上互联网行业BD拓展工作经验，toB模式优先考虑；", "2、较强的商务拓展能力和谈判能力，可以独立对外开展商务合作；", "3、较强的项目策划能力，能根据自身的资源和优势，并结合客户具体情况制定相应的合作方案。", "4、良好的人际沟通能力、决策分析能力和信息整合能力，以及较强的项目执行能力。"]},
{"name": "资深用户运营（内容运营方向）-杭州-网易严选", "link": "https://hr.163.com/position/detail.do?id=20003", "address": "杭州市", "cotegory": null, "type": "电商>电商运营", "num": "1人", "duty": ["1、负责严选电商相关频道、栏目规划、创新运营工作，对内容流量负责。", "2、负责爆品整合营销策划，包含推进线上线下、站内外的联合推广计划。", "3、负责CMS内容管理系统的搭建，跟踪和分析产品数据，调整运营节奏，不断完善内容产品功能。"], "requir": ["1、本科及以上学历，3年以上内容运营、平台运营、产品运营相关经验，电商、新媒体、广告等经验者相关经验优先。", "2、内容敏感度高，对热点内容具有敏锐洞察，善于挖掘、捕捉、产出优质内容。", "3、具有一定数据分析能力，能够挖掘、分析数据并优化产品。", "4、具备独立完成内容产品架构、策划能力，深刻理解互联网产品和模式，准确把握用户心理。", "5、对PGC内容运营有深入研究，对产品及平台运维有思考及经验。"]},
{"name": "资深用户运营（社群方向）-杭州-网易严选", "link": "https://hr.163.com/position/detail.do?id=20004", "address": "杭州市", "cotegory": null, "type": "电商>电商运营", "num": "1人", "duty": ["1、负责严选电商相关频道、栏目规划、创新运营工作。", "2、负责内容社群运营，重点推进社群用户的内容管理，核心用户引进及维护，实现超级会员的留存和成长。", "3、负责策划用户活动，推广优质UGC内容，提高认知度，制定粉丝互动策略，提升社群活跃度。", "4、挖掘社群运营模式，跟踪和分析产品数据，调整运营节奏。"], "requir": ["1、本科及以上学历，2年以上用户、社区运营相关经验，电商相关经验优先。", "2、内容敏感度高，对热点内容具有敏锐洞察，善于挖掘、捕捉、产出优质内容。", "3、具有一定数据分析能力，能够挖掘、分析数据并优化产品。", "4、具备独立完成内容产品架构、策划能力，深刻理解互联网产品和模式，准确把握用户心理。", "5、对UGC、PUGC内容运营有深入理解，对社区运营有热情及思考。", "6、对产品和运营数据敏感，了解用户体验的要素，善于倾听用户声音，了解用户及用户需求，注重用户感受及体验；"]},
{"name": "资深用户运营（付费会员方向）-杭州-网易严选", "link": "https://hr.163.com/position/detail.do?id=20002", "address": "杭州市", "cotegory": null, "type": "电商>电商运营", "num": "1人", "duty": ["1. 主要负责网易严选付费会员的续费留存与回流升级，包括其日常服务，触达手段、资源通道和运营策略的整体规划。", "2．利用个性化、精细化运营手段，提升用户体验，提升付费会员的续费留存和升级回流，实现用户增长，降低用户转化成本；", "3．挖掘用户需求，探索增长点，分析用户运营数据，根据数据分析提出产品构想、策略优化等。", "4．制定付费会员续费留存和升级回流的营销计划，并跟进效果和制定完善的优化策略。"], "requir": ["1.本科及以上学历，熟悉互联网/电商行业，至少3年以上用户产品运营经验；", "2.擅长数据化运营，逻辑清晰，能洞察数据背后的用户需求和行为逻辑，以结果为导向，注重数据与量化；", "3.对互联网用户行为与心理，有较高敏感性与洞察力，有一定自己的见解与思考。具备一定的产品思维，用产品的手段解决问题的能力；", "4.良好的沟通和主动学习能力，自驱力强，有较强的团队协作能力和抗压能力，根据业务目标和计划快速展开工作，主动协调相关业务方完成项目推进。"]},
{"name": "资深用户运营（用户增长方向）-杭州-网易严选", "link": "https://hr.163.com/position/detail.do?id=20001", "address": "杭州市", "cotegory": null, "type": "电商>电商运营", "num": "1人", "duty": ["1.负责用户承接及增长运营，重点针对1转2单用户，包括其日常服务，运营策略制定，资源通道和营销整体的把控；", "2.利用个性化、精细化运营手段，提升用户体验，提升新客复购和留存，降低用户转化成本；", "3.挖掘用户需求，探索增长点，分析用户运营数据，根据数据分析提出产品构想、策略优化等；", "4.具备一定活动策划能力，并为活动效果负责，分析和联动活动和策略的效果；", "5.定期关注竞品动态与行业情况，不断推动项目优化运营效果。"], "requir": ["1.本科及以上学历，熟悉互联网/电商行业，3年以上用户产品运营经验；", "2.擅长数据化运营，逻辑清晰，能洞察数据背后的用户需求和行为逻辑，以结果为导向，注重数据与量化；", "3.对互联网用户行为与心理，有较高敏感性与洞察力，有一定自己的见解与思考。具备一定的产品思维，用产品的手段解决问题的能力；", "4.良好的沟通和主动学习能力，自驱力强，有较强的团队协作能力和抗压能力，根据业务目标和计划快速展开工作，主动协调相关业务方完成项目推进。"]},
{"name": "资深电商运营（京东）-杭州-网易严选 - 严选事业部001", "link": "https://hr.163.com/position/detail.do?id=20768", "address": "杭州市", "cotegory": null, "type": "电商>电商运营", "num": "1人", "duty": ["1.负责网易严选京东旗舰店的店铺运营管理工作，包括货品运营、流量运营、活动运营、用户运营；", "2.依据公司整体销售目标进行分解，制定完善的货品策略以及平台营销策略，带领团队完成销售目标，对销售负责；", "3.根据公司的发展方向及京东平台的发展趋势，制定店铺阶段性短期目标及长期发展方向；", "4.善于发掘平台营销工具与营销手段，为店铺及商品导流，根据店铺产品属性，自主设计店内的各种营销活动并跟进执行细节；", "5.善于跟京东的采销沟通，获取平台资源，并做好销售承接；", "6.能够进行专业的数据分析及平时做好竞争对手网站的数据的评估与分析。"], "requir": ["1.电子商务、市场营销、经济管理类或相关专业本科以上学历；", "2.3-5年以上电子商务工作经验，有京东店铺运营经验者优先；", "3.具有店铺整体运营规划能力，品牌/产品定位能力；", "4.对国内电子商务现状有清晰的认识，对电子商务的运作模式有深刻的理解，精通网络营销；", "5.具备优秀的市场分析、客户分析、市场推广与策划能力；", "6.具有优秀的资源整合能力和业务推进能力；", "7.熟悉居家、快消类商品运营经验者优先，或全品类运营经验者优先。"]},
{"name": "资深大客户运营专员-上海-网易严选", "link": "https://hr.163.com/position/detail.do?id=20544", "address": "上海市", "cotegory": null, "type": "销售>销售支持", "num": "1人", "duty": ["1、负责TO B 业务场景运营，包括但不限于：日常活动提报，平台推广位获取、类目主题活动策划、营销专题内容策划及提报等电商运营工作；", "2、负责大客户资源整合及运营方案输出，需挖掘客户真实需求，有针对性的定制运营方案，满足多方需求并且推进实施上线，完成销售目标；", "3、 针对不同B端平台特质，通过关键词优化及各类营销推广手段，打造爆款商品，有效提升销售额；", "4、 协调美工优化页面，对专区或产品访问量、转化率数据进行分析，并实施改进方案；", "5、 全力迎战全年的重要活动节点，快速形成销量。"], "requir": ["1、全日制本科以上学历，电子商务、市场营销类或相关专业优先；", "2、5年以上电子商务或重点金融渠道运营经验，业绩优秀，具备食品、家居品类行业经验尤佳；", "3、熟悉TO B 业务场景，包括不限于积分兑换渠道、福利平台现、营销礼赠等；", "4、具备TOB渠道运营导向的商品折扣、节日活动和全生命周期运营管理及促销经验；", "5、具有优秀的数据分析、资源整合、业务推进能力。同时有良好的团队合作意识。"]},
{"name": "大客户销售经理-杭州-网易严选", "link": "https://hr.163.com/position/detail.do?id=20008", "address": "杭州市", "cotegory": null, "type": "电商>电商综合", "num": "1人", "duty": ["1、负责严选产品在集团客户和潜在大客户的开发、拓展、维护、销售工作", "2、负责2B行业客户的沟通、谈判、签约及回访、维护工作", "3、不断挖掘客户潜在价值，促成多场景合作，包括不限于积分兑换、营销礼赠、员工福利等。以达成客户与公司间最大价值的合作方式", "4、5年以上工作经验，2年以上2B企业行业背景", "5、有成熟的ToB企业销售成功经验或是项目经验"], "requir": ["1、5年以上互联网行业BD拓展工作经验，toB模式优先考虑；", "2、较强的商务拓展能力和谈判能力，可以独立对外开展商务合作；", "3、较强的项目策划能力，能根据自身的资源和优势，并结合客户具体情况制定相应的合作方案。", "4、良好的人际沟通能力、决策分析能力和信息整合能力，以及较强的项目执行能力。"]},
{"name": "家具/家居产品设计师-杭州-网易严选", "link": "https://hr.163.com/position/detail.do?id=19738", "address": "杭州市", "cotegory": "严选事业部", "type": "设计>工业设计", "num": "1人", "duty": ["1.负责大居家品类家具 / 灯具 / 家饰等产品研发设计；", "2.主导产品线整体风格定位及趋势设计，协同商品部制定家具品类设计规划；", "3.协助商品部选品，参与方案讨论，提出专业意见；", "4.从品牌层面输出产品设计语言及设计逻辑，打磨设计细节，提升产品体验；", "5.可独立且完整的输出设计BRIEF，并有计划性的把控好与合作方的产出，包括但不局限于：指导外部团队完善与深化设计图纸 ，对接供应商跟进产品打样、试样、量产,解决设计和结构问题。"], "requir": ["1.国籍不限，3年以上国内外家具/家居产品设计经验，优秀设计院校本科及以上学历，有一线家具品牌或顶尖家具设计事务所产品设计经验者优先；", "2.熟练操作Rihno/3D max/Illustrator/CAD/渲染/PS/AI等设计软件；", "3.了解结构设计、熟悉家具材质及五金件应用；", "4.国际化的视野，能用中文进行日常工作沟通，具有较高的设计美学素养及良好的沟通和表达能力。"]},
{"name": "资深产品运营 - 严选事业部001", "link": "https://hr.163.com/position/detail.do?id=19461", "address": "杭州市", "cotegory": "严选事业部", "type": "电商>电商运营", "num": "1人", "duty": ["1、负责严选APP核心资源位排期、对运营数据进行监控，进行有效分析，提升资源利用效率最大化", "2、负责跟踪资源位核心指标，制定分配规则及考核标准。", "3、负责跨部门沟通协调各业务方资源需求，形成周期性复盘报告，保证排期合理性。", "4、针对资源投放系统根据核心指标提出策略性优化建议，推动产品功能完善"], "requir": ["1、本科及以上学历，2年电商工作经验，有大型电商平台资源运营经验优先", "2、有较强的逻辑能力，对数据敏感，灵活多变的工作方式和抗压性，以目标为导向", "3、有创意和文案功底，具备较强的抗压能力和执行力，有良好的团队意识和沟通技巧", "4、对热点、用户需求等有极强的敏感度，能够及时提出有针对性和创意的优化建议", "5、熟悉网易严选模式，了解网易严选产品优先"]},
{"name": "资深内容运营（直播）-杭州-网易严选", "link": "https://hr.163.com/position/detail.do?id=19054", "address": "杭州市", "cotegory": "严选事业部", "type": "电商>电商综合", "num": "1人", "duty": ["1. 负责直播带货和短视频拉新，在视频生态中，通过自建/合作内容的方式实现向电商app导流，并可规模化复制；", "2. 构建网易严选电商视频/直播/短视频内容合作生态，通过搭建直播体系，创造性的内容创作者及内部主播团队的激励体系，与一批内容创作者或机构形成长期稳固的合作关系；", "3. 维护和开拓内容合作者或机构资源；", "4. 具备敏锐的商品感知，能够充分挖掘和运用商品卖点塑造内容及传播；"], "requir": ["1. 对MCN、网红经济、微博、微信、抖音、小红书、快手等新媒体有一定了解，有短视频运营经验优先； ", "2. 熟悉自媒体行业，了解MCN机构运作流程及对外合作机制； ", "3. 有较强的组织协调能力和沟通能力、解决问题的能力和抗压能力； ", "4. 具有较强的商品敏感度，内容策划能力，逻辑以及独立思考能力； "]},
{"name": "资深会员运营-杭州-网易严选", "link": "https://hr.163.com/position/detail.do?id=20361", "address": "杭州市", "cotegory": null, "type": "电商>电商综合", "num": "1人", "duty": ["1.网易严选的等级会员的业务负责人，主要负责等级会员得留存于增长及积分运营体系的统筹。通过积分体系促活促转化，同时重点引导等级会员往高等级迁移，实现核心用户的增长与留存，包括其日常服务，触达手段、资源通道和运营策略的整体规划。", "2．利用个性化、精细化运营手段，促进用户不断复购，扩大核心用户的规模与销售贡献，实现用户的留存于增长，降低用户转化成本；", "3．整体布局积分体系，并优化迭代积分任务体系，打造具有记忆性的栏目，实现促活、促转化、促连带的目标。", "4．挖掘用户需求，探索增长点，分析用户运营数据，根据数据分析提出产品构想、策略优化等。", "5．制定会员留存和高阶迁移的营销计划，并跟进效果和制定完善的优化策略。"], "requir": ["1.本科及以上学历，熟悉互联网/电商行业，至少4-5年以上用户产品运营经验；有过会员/积分运营经验者优先；", "2.擅长数据化运营，逻辑清晰，能洞察数据背后的用户需求和行为逻辑，以结果为导向，注重数据与量化；", "3.对互联网用户行为与心理，有较高敏感性与洞察力，有一定自己的见解与思考。具备一定的产品思维，用产品的手段解决问题的能力；", "4.良好的沟通和主动学习能力，自驱力强，有较强的团队协作能力和抗压能力，根据业务目标和计划快速展开工作，主动协调相关业务方完成项目推进。"]},
{"name": "电商平台资源管理-杭州-网易严选", "link": "https://hr.163.com/position/detail.do?id=19583", "address": "杭州市", "cotegory": null, "type": "电商>电商运营", "num": "1人", "duty": ["1、负责严选APP核心资源位排期、对运营数据进行监控，进行有效分析，提升资源利用效率最大化", "2、负责跟踪资源位核心指标，制定分配规则及考核标准。", "3、负责跨部门沟通协调各业务方资源需求，形成周期性复盘报告，保证排期合理性。", "4、针对资源投放系统根据核心指标提出策略性优化建议，推动产品功能完善"], "requir": ["1、本科及以上学历，5年电商工作经验，有大型电商平台资源运营经验优先", "2、有较强的逻辑能力，对数据敏感，灵活多变的工作方式和抗压性，以目标为导向", "3、有创意和文案功底，具备较强的抗压能力和执行力，有良好的团队意识和沟通技巧", "4、对热点、用户需求等有极强的敏感度，能够及时提出有针对性和创意的优化建议", "5、熟悉网易严选模式，了解网易严选产品优先"]},
{"name": "资深活动运营-杭州-网易严选", "link": "https://hr.163.com/position/detail.do?id=20595", "address": "杭州市", "cotegory": null, "type": "电商>电商综合", "num": "1人", "duty": ["1、主要负责严选S级大促（周年庆、双11、618、双12等）的营销策划工作", "2、协同大促期间的货品管理与定价，控制全站的利润与销售额", "3、负责活动后的数据分析及复盘，产出更优化的方案，提升整体活动运营效果", "4、独立撰写卖场策划方案，跨部门沟通业务需求，与营销、产品、设计、研发等团队一起推动营销活动执行落地", "5、设计并落地互动活动玩法作为营销突破点，以互动游戏、创意视频等玩法驱动用户自传播，吸引流量"], "requir": ["1、本科以上学历；互联网/电商公司5年以上从业经验；", "2、对活动策划有经验，特别是双11,618等电商大促有运营经验者优先；", "3、熟悉AXURE等原型工具，具备优秀的产品化思维。", "4、创新能力强，有持续写作或有较好的文字功底；逻辑清晰者优先", "5、结果导向，注重数据与量化，学习能力强。", "6、具有较强的学习能力及团队合作精神，抗压能力强；有很强的组织协调、沟通能力。"]},
{"name": "商品设计师-广州-网易严选", "link": "https://hr.163.com/position/detail.do?id=20548", "address": "广州市", "cotegory": null, "type": "设计>商品设计", "num": "1人", "duty": ["1.负责严选商品设计、包装设计（家电数码及潮流产品方向）", "2.能够独立完成从概念设计到3D效果图输出，有一定手绘基础", "3.结合竞品和行业趋势参与设计研究"], "requir": ["面向人群：海内外院校2021、2022届毕业生", "1.熟练掌握PS、AI、C4D等设计软件", "2.对造型、色彩、工艺、表面处理有基本的认知，熟悉包装材质工艺", "3.具备良好的审美和创造力，热爱生活，有脑洞，能驾驭年轻化、潮流化的设计风格 "]},
{"name": "杭州_高级/资深前端开发工程师 - 项目管理中心600", "link": "https://hr.163.com/position/detail.do?id=20445", "address": "杭州市", "cotegory": null, "type": "技术>研发类", "num": "3人", "duty": ["1、加入效率工程部门，参与企业协作办公平台研发，共同打造卓越工具服务；", "2、包括参与项目技术方案制定、技术评审、代码审核、内部技术交流分享等；", "3、对前沿技术保持敏感，协助推进项目技术服务升级，持续发展。"], "requir": ["1、计算机及相关专业，3年以上前端开发经验；", "2、能够深入理解 Anglur/React/VUE 等前端框架，并能够独立完成 10 行万以上项目架构；", "3、精通 JavaScript 语言,能够脱离各 JS 类库后熟练的进行跨浏览器开发；", "4、熟练掌握跨原生端开发（对于Electron、Flutter或者RN有实践经验）；", "5、关注前端发展，熟练掌握 W3C 关于Ecmascript、HTML、CSS 的相关标准；", "6、对 Web 下层的 HTTP 协议、TCP/IP、DNS 等熟练掌握，并能够利用相关知识解决项目问题者优先；", "7、具备浏览器源码及 JavaScript 引擎源码阅读能力者优先；", "8、掌握跨小程序开发或熟悉IOS Android开发优先。"]},
{"name": "零售店运营总监 - 网易严选", "link": "https://hr.163.com/position/detail.do?id=19607", "address": "杭州市", "cotegory": "严选事业部", "type": "电商>电商综合", "num": "1人", "duty": ["1.负责网易严选全国零售店生意发展和团队管理", "2.搭建高效的连锁加盟体系，实现网易严选零售店从1到100的快速发展", "3.负责零售店商业模式P/L，实现网易严选和合作伙伴双赢", "4.领导网易严选零售店团队"], "requir": ["1.8-10年知名零售行业管理经验", "2.丰富的品类管理知识和连锁加盟管理能力", "3.丰富的区域门店运营能力和人员管理经验"]},
{"name": "游戏用户研究员-广州-用户体验中心", "link": "https://hr.163.com/position/detail.do?id=12660", "address": "广州市", "cotegory": "互动娱乐事业群", "type": "用户体验>用户研究类", "num": "3人", "duty": ["1. 参与网易游戏产品的研发过程，提供用户研究工作支持；", "2. 熟练运用各种用户研究方法，跟进网易游戏产品研发各个阶段，提供客观的产品体验度量结果以及合理的用户体验提升策略；", "3. 关注运营数据和用户反馈，评估、跟进、促使产品提升用户体验；", "4. 构建产品用户体验设计标准，跟踪和监督产品用户体验等的改进，提升产品质量；"], "requir": ["1. 本科或以上学历，专业不限，具有优秀的执行与分析能力；", "2. 有深入的游戏体验经历，热爱游戏者；", "3. 有1年以上用户体验/研究相关岗位经验优先；", "4. 能熟练应用主流研究与分析工具、方法； ", "5. 优秀的责任心、沟通能力、推动能力以及出色的服务意识；", "6.请务必在简历中详细说明个人游戏经历。"]},
{"name": "高级活动运营-杭州-网易严选 - 严选事业部001", "link": "https://hr.163.com/position/detail.do?id=20727", "address": "杭州市", "cotegory": null, "type": "电商>电商运营", "num": "1人", "duty": ["1. 以创造新消（未购）用户良好体验，打造严选品牌的用户心智为目标，负责严选站内新消用户相关的页面、栏目、商品运营策划，包括内容呈现、选品、活动策划等；", "2. 与市场效果投放部门联动，了解新消用户的渠道来源和转化场景，有针对性地优化流量在站内的落地运营，提高新消用户转化；", "3. 通过数据分析和复盘，协同商务、产品等其他部门持续优化选品、内容和用户体验，不断寻找增加新消用户转化的机会点。"], "requir": ["1. 本科及以上学历，2年以上电商类目/活动运营经验，深度了解电商用户和选品运营，有大型综合平台运营工作经验为佳；", "2. 对用户有洞察，对数据有敏感性，能够从数据中挖掘问题，提供解决方案；", "3. 逻辑清晰，思维开阔，有一定创新能力；", "4. 有很强的责任感和自驱力；", "5. 善于沟通和跨部门协作"]},
{"name": "资深结构设计师 - 严选事业部007", "link": "https://hr.163.com/position/detail.do?id=19437", "address": "杭州市", "cotegory": "严选事业部", "type": "设计>工业设计", "num": "1人", "duty": ["1.参与产品方案设计，负责新产品开发中各阶段评审，试模，参与结构设计评估，组织协调结构跟进工作； ", "2.负责解决新产品开发各阶段出现的结构技术等相关问题； ", "3.负责单个商品部件结构设计或优化工作； ", "4.制定产品相关技术文档； ", "5.负责产品模具加工督导与跟进，开模前评估，试模检验、模具验收。"], "requir": ["1.机械设计相关专业毕业，本科以上学历，具有5年以上消费类产品结构设计工作经验；", "2.熟悉小家电的结构设计要求，熟悉塑件加工工艺，熟悉产品工艺，具有相关结构设计的成功经验和模具开发跟踪等方面的经验； ", "3.掌握常用材料、表面处理工艺、各类加工工艺等专业知识； ", "4.熟练使用如：PROE、AUTO CAD等相关设计软件； ", "5.具备一定的供应链资源，熟悉相关行业规范及国家标准，能输出Boom表； ", "6.善于沟通和表达，工作认真负责，注重细节，执行力强。"]},
{"name": "高级／资深CMF设计师 - 严选事业部007", "link": "https://hr.163.com/position/detail.do?id=19434", "address": "杭州市", "cotegory": "严选事业部", "type": "设计>商品设计", "num": "1人", "duty": ["1.色彩材料趋势研究、分析与整理，材料工艺相关性能技术研究与解决； ", "2.开发、整理、维护公司的色板库及样品库；配合结构、资源对新材料新工艺进行评估并导入工艺库；", "3.配合商品设计师做好项目的配色、打样、问题反馈与跟进，对于项目量产能够给出专业的工艺建议； ", "4.保证项目节点，与品质部门一起做好标准样以及Color QA的相关判定工作。 "], "requir": ["1.工业设计相关专业，5年以上相关CMF 材料工艺开发经验，熟练掌握工业设计领域专业知识及材料知识； ", "2.设计视野广阔，具备敏锐的时尚感受，良好的审美和色彩感知力； ", "3.熟练使用相关渲染软件以及平面软件；思路清晰，能够以平面及实体的各式素材呈现并传达CMF设计概念； ", "4.对各种材料与工艺创新抱有热忱；对不同的领域抱有好奇心及求知欲； ", "5.良好的沟通和团队协作意识。"]},
{"name": "资深活动营销-杭州-网易严选 - 严选事业部001", "link": "https://hr.163.com/position/detail.do?id=20735", "address": "杭州市", "cotegory": null, "type": "电商>电商综合", "num": "1人", "duty": ["1、挖掘网易严选生意增长点，洞察用户需求，在严选大促节点（618，双11等），制定活动营销打法和策略。并通过营销创意，实现品牌好感度和业务增长。", "2、洞悉品牌内核，通过以社会化玩法为主的整合营销，如话题炒作/事件营销/娱乐营销等手段，以小博大，创造品牌价值。", "3、与运营，产品，技术及商品等团队沟通协作，通过营销反驱动端内，实现业务目标。", "4、项目目标预设与结果复盘，拆解KPI并通过数据化的手段评估结果。"], "requir": ["1、互联网/广告行业5年以上经验，操盘过爆款项目或产品增长项目优先。", "2、具备创意能力，对舆论环境敏感。擅长探索新的营销方式并综合运用。", "3、有职业追求和自驱力，能够快速推进项目，执行力强。"]},
{"name": "资深用户运营 /CRM Leader-杭州-网易严选", "link": "https://hr.163.com/position/detail.do?id=20419", "address": "杭州市", "cotegory": null, "type": "电商>电商综合", "num": "1人", "duty": ["1、网易严选用户留存与复购负责人，负责网易严选用户新客复购与老客留存的规划、策略制定与落地执行。", "2、负责搭建用户生命周期管理体系、每月用户召回计划等日常运营工作内容", "3、通过创新性的召回项目、定向活动等各种运营手段，提高留存率与新客复购率，从而提升老客支付人数，达成销售目标。", "4、制定CRM系统产品需求，优化各种用户触达手段，提高精准营销效率。"], "requir": ["1、有五年以上运营经验、三年以上用户运营经验，电商类用户运营经验优先", "2、有较强的责任感，积极主动，性格开朗。有较优秀的策划、文案能力，广告、新闻、文学等专业优先考虑。", "3、逻辑清晰，有一定数据敏感性，会从数据角度发现并解决问题。", "4、抗压能力强，思维活跃，有创意，为人细心。"]},
{"name": "Web前端开发工程师 -广州", "link": "https://hr.163.com/position/detail.do?id=20677", "address": "广州市", "cotegory": "互动娱乐事业群", "type": "技术>研发类", "num": "2人", "duty": ["1. 参与网易游戏数据平台及相关数据产品的前端开发工作；", "2. 参与具体需求的开发流程，与服务端开发、设计、产品人员沟通，保证产品的质量和开发进度；", "3. 负责前端工程化建设，包括业务组件开发，性能优化，提升产品用户体验；"], "requir": ["1、计算机及相关专业本科以上学历,2年以上Web前端开发经验；", "2、精通Web前端相关技术(HTML/CSS/JavaScript/ES6等)，熟悉至少一个主流开发框架（react/vue/angular等）；", "3、热爱学习，关心新技术的发展，具有深入研究的兴趣和能力；", "4、良好的沟通能力和团队合作精神", "5、加分项：了解服务端开发技术（如SpringBoot/NodeJs等），了解数据库（如MySql/Oracle/MongoDB/Redis等），了解前端可视化、脚手架组件(如 jsPlumb/G6/Ant Design 等)；"]},
{"name": "高级商务拓展专员- 网易严选", "link": "https://hr.163.com/position/detail.do?id=19647", "address": "杭州市", "cotegory": "严选事业部", "type": "销售>销售", "num": "1人", "duty": ["负责网易严选线下店，包括商场Shopping Mall、高新园区等商业资源的选址、商业地产、物业资源的商务拓展、门店开发工作", "负责国内区域城市伙伴人的开拓与商务谈判", "负责国内区域加盟商的拓展与商务谈判"], "requir": ["1.大学本科及以上学历，有3-5年以上线下渠道开拓、连锁门店开发经验，熟悉从门店选址、项目评估、商务条件谈判整体流程和各关键控制点", "2.在大型、知名零售连锁公司工作经验者优先", "3.有加盟商资源与经验优先", "4.对数据敏感，具备数据化管理能力", "5.具备良好的学习力、执行力、沟通表达能力，抗压能力强，能不断迎接变革与挑战，工作态度严谨且坚守原则   ", "6.具备良好的团队协作能力"]},
{"name": "资深栏目运营-杭州-网易严选", "link": "https://hr.163.com/position/detail.do?id=18153", "address": "杭州市", "cotegory": "严选事业部", "type": "电商>电商运营", "num": "1人", "duty": ["1、负责网易严选APP及PC现有栏目的日常运营，如选品、排期、商品管理等", "2、负责栏目流量的使用规划及日常流量分配，制定合理KPI指标", "3、了解竞品及用户需求，探索栏目营销玩法，对引入新用户、提高老用户活跃度、销售指标负责", "4、对栏目数据进行追踪及分析，定期对自身产品、整体行业、竞品等进行数据分析评估，优化栏目运营效果", "5、跨部门沟通协作，与营销、产品、设计、研发等团队一起推进栏目质量及产品更新迭代"], "requir": ["1、本科及以上学历，5年以上电商工作经验，深度了解用户运营、频道运营，有大型综合平台运营工作经验为佳", "2、学习能力强，基于深度理解业务，有优化流程和资源调配的意识", "3、对产品的解决方案有成熟的判断决策能力，逻辑清晰，思维开阔，具备较强的总结归纳能力及优秀的沟通能力和跨部门协作能力", "4、对用户需求、数据等有极强的敏感度，对运营工作有激情", "5、有相关项目经验、产品经理经验优先", "6、熟悉网易严选模式，了解网易严选产品优先"]},
{"name": "高级流程内控-杭州-网易严选", "link": "https://hr.163.com/position/detail.do?id=19885", "address": "杭州市", "cotegory": "严选事业部", "type": "电商>电商综合", "num": "1人", "duty": ["1.遵循体系标准执行落地，负责所对接业务板块的内控风险管理；", "2.流程管理及优化：与业务部门协作，管理新流程或优化后流程的落地和推行;（CR管理、建设/优化、推行执行、稽核监察、效果评估PDCA）", "3.负责监督、报告各板块内控工作执行情况，向管理层报告公司整体内控状况。", "4.实施内控培训、宣传，增强相关部门人员的内部控制意识，降低风险发生率；", "5.将通过内控BP角色，深入挖掘业务部门利益点与痛点，协助所负责业务板块负责人建立并完善内控系统，提高业务风险承担水平，提升经营效率效果，最终达成战略目标。"], "requir": ["1、3年或以上大型企业/上市公司风险管理、内部控制、流程管理等相关工作经验，主要侧重销售业务控制、信息系统控制等工作经验者优先。电商企业、四大事务所或专业内控咨询公司经验者优先；", "2、具有丰富的风险管理工作经验，掌握风险评估诊断、风险识别、分析、研判等技能，并具有良好的业务敏感性及理解能力；", "3、逻辑性强，具有较强的沟通协调、独立分析和判断能力，并思辨执行，擅长归纳总结发现问题能力及解决问题能力；", "4、具备优秀的职业素养与品德操守，责任心强，能承受较大工作压力，具备快速学习、理解业务的能力；", "5、具备核心业务资格证书或CIA、CPA、CICS等优先。"]},
{"name": "大客户销售经理-北京-网易严选", "link": "https://hr.163.com/position/detail.do?id=14504", "address": "北京市", "cotegory": "严选事业部", "type": "销售>销售", "num": "1人", "duty": ["1、负责严选产品在集团客户和潜在大客户的开发、拓展、维护、销售工作", "2、负责2B行业客户的沟通、谈判、签约及回访、维护工作", "3、不断挖掘客户潜在价值，促成多场景合作，包括不限于积分兑换、营销礼赠、员工福利等。以达成客户与公司间最大价值的合作方式", "4、5年以上工作经验，2年以上2B企业行业背景", "5、有成熟的ToB企业销售成功经验或是项目经验"], "requir": ["1、5年以上互联网行业BD拓展工作经验，toB模式优先考虑；", "2、较强的商务拓展能力和谈判能力，可以独立对外开展商务合作；", "3、较强的项目策划能力，能根据自身的资源和优势，并结合客户具体情况制定相应的合作方案。", "4、良好的人际沟通能力、决策分析能力和信息整合能力，以及较强的项目执行能力。"]},
{"name": "资深公关媒介专员-杭州-网易严选", "link": "https://hr.163.com/position/detail.do?id=20380", "address": "杭州市", "cotegory": "严选事业部", "type": "电商>电商综合", "num": "1人", "duty": ["1、媒体关系的开拓与深入挖掘，媒体合作谈判，日常媒体关系维护； ", "2、结合媒体特征，主动策划选题内容，制订撰稿计划以及传播规划，并统计并分析传播效果； ", "3、统筹中大型媒体活动，如发布会、沟通会等； ", "4、危机舆情预警以及处理；"], "requir": ["1、在互联网行业3-5年媒体相关工作经验； ", "2、性格开朗，擅长沟通； ", "3、拥有丰富的媒体资源，熟悉媒体传播生态，有较强的策划、撰稿能力； ", "4、本科以上学历，新闻或中文相关专业优先； ", "5、有国内知名媒体工作3年以上者优先；"]},
{"name": "前端开发工程师", "link": "https://hr.163.com/position/detail.do?id=20577", "address": "杭州市", "cotegory": null, "type": "技术>研发类", "num": "2人", "duty": ["1.负责前端页面的设计、开发、维护工作，配合后台开发人员完成项目，提升产品UI效果、用户体验", "2.前端模块化、工程化的实现及优化，持续改进产品性能、稳定性和可扩展性"], "requir": ["1.计算机及相关专业本科以上学历，2年以上Web前端开发经验", "2.熟练掌握 HTML、JS、CSS 等前端技术，熟悉页面架构和布局，对表现与数据分离、Web语义化等有深刻理解", "3.熟练掌握 Vue2.x / React / AngularJS 中的至少一种前端框架，并了解其原理", "4.熟悉前端工程化、组件化、模块化的开发模式并实践", "5.对前端性能优化、多浏览器兼容性问题等有过研究和实践", "6.善于学习和运用新知识，善于沟通和逻辑表达，有强烈的团队意识和执行力", "7.对后端技术（如 JAVA, MongoDB/MySQL 等）和开发模式有一定了解的优先", "8.对用户体验、交互操作流程及用户需求有较深理解的优先"]},
{"name": "数据标注工程师（英语方向） -广州", "link": "https://hr.163.com/position/detail.do?id=20736", "address": "广州市", "cotegory": "互动娱乐事业群", "type": "职能>行政类", "num": "1人", "duty": ["职位描述：", "主要工作内容是根据给定的文本（英文）、图像、语音等材料，按照要求进行整理、标注和统计。", "岗位职责：", "1.根据给定的音频文件（英文）、图像、文本等材料，能准确识别语义以及翻译成对应文本；", "2.工作效率高，保证标注结果的准确率、合格率；", "3.有效地汇报进度和反馈数据问题，善于与其他部门进行团队合作。"], "requir": ["1.全日制大专及以上学历，熟悉微软办公室套件的使用；", "2.英语CET-6以上，听说读写熟练，有相关翻译经验者优先；", "3.对文本、图像等数据内容敏感，有良好的阅读理解能力；", "4.主动学习，沟通和表达顺畅，认真负责有耐心；", "5.具有安全保密意识，不传播工作内容；", "6. 有游戏经验者或有数据标注，知识库搭建、有编程经验者优先"]},
{"name": "资深数据分析师 - 音乐事业部028", "link": "https://hr.163.com/position/detail.do?id=15133", "address": "杭州市", "cotegory": "音乐事业部", "type": "技术>数据分析与管理", "num": "2人", "duty": ["1、支持业务需求，完成部门内部交付的数据分析和挖掘任务； ", "2、对业务问题进行深入分析，能对关键分析思路进行产品化；", "3、具有较强的团队合作精神，数据驱动业务迭代发展，沉淀分析框架；", "4、有toc产品分析经验者优先。"], "requir": ["1、本科及以上学历，数学、统计学、计算机专业优先；", "2、3年以上互联网数据分析经验，具备统计业务背景，大量数据处理经验，对用户分析、运营分析有深刻见解； ", "3、有一定的创新能力，在以往的数据分析、挖掘等工作中有自己独特的见解； ", "4、具有较强的逻辑思维能力、数据洞察能力和沟通协调能力，拥有强烈的责任心和团队合作精神； ", "5、具有探索精神，从数据中发现价值用以支持决策； ", "6、熟练掌握数据分析工具和技术，比如SQL、R、SPSS、Excel、SAS等； 7、熟练掌握统计学方法，较强数学逻辑，对数据有较强敏感度。"]},
{"name": "Trade Marketing Leader - 网易严选", "link": "https://hr.163.com/position/detail.do?id=20297", "address": "杭州市", "cotegory": null, "type": "电商>电商综合", "num": "1人", "duty": ["1. 负责制定，计划和执行网易严选零售分销渠道营销活动，包括零售店，分销大客户和海外渠道。根据严选品牌和主站活动主题，制定全渠道营销计划", "2. 负责网易严选品牌参与重点客户的营销活动，促进销售，毛利和用户增长", "3. 制定不同渠道的渠道策略，促进网易严选各个品类生意在不同渠道的分销和市场份额", "4. 负责渠道助销工具的设计，生产和执行，确保严选品牌在各个渠道可视性", "5. 定期的渠道营销报表和生意回顾", "2. 负责管理渠道营销预算，确保实际花费ROI和在预算以内"], "requir": ["1. 本科以上学历", "2. 至少5年以上知名快消公司销售和Trade Marketing工作经验，具备传统渠道和现代零售渠道经验", "3. 好的领导力，自我驱动力和主人翁精神"]},
{"name": "Project Manager(Montreal) - 雷火项目管理部", "link": "https://hr.163.com/position/detail.do?id=18435", "address": "国外", "cotegory": "雷火事业群", "type": "技术>项目管理", "num": "1人", "duty": ["Job Description", "NetEase Games Montreal is the brand new division of NetEase Games; a leading game developer and publisher focusing on delivering top quality mobile and online gaming experiences. We’re currently looking for a Project Manager who can help us manage project and coordinate with development team in China.", "Job Responsibilities:", "• Ensure that the various planning, communication and tracking tools are properly implemented and updated;", "• Cooperating with China development teams to ensure the local Montreal team is in order, including plans from the start of the project to the launch;", "• Assisting team building and timely summarize and synchronize project information to relevant stakeholders;", "• Responsible for putting together documentation packages required to go through all the approval & certification process phases with first parties;", "• Follow-up with the managers and update the staffing plans for the project team;"], "requir": ["• Minimum of 5 years’ experience in coordinating game development, operations, project management;", "• Passionate on the game and game industry, with software development experience;", "• Bachelor degree or above, with strong project management skills;", "• Strong communication and coordination skills, team leadership and self-motivation for continuous learning;", "• Ability to work in high-pressure environment, and to adapt to multi-task management, high work intensity and cross-time zone communication;", "• Working knowledge of agile development methodologies such as Scrum;", "• PMP Certificate is a plus", "• Ability to communicate in Mandarin is a plus."]},
{"name": "虚拟角色研究员 - 伏羲实验室004", "link": "https://hr.163.com/position/detail.do?id=14919", "address": "杭州市", "cotegory": "伏羲实验室", "type": "技术>人工智能", "num": "3人", "duty": ["虚拟偶像/智能虚拟人是一款能够通过语言，面部表情，眼神交互和肢体语言与真人用户实时交流的软件系统。", "虚拟偶像与用户交流时，它能够像人类一样表达意图和情感，同时还能够通过用户的语音和行为解读用户的情感和意图。", "该项目涵盖了多个研究方向，包括多模态融合/交互，情感计算，机器视觉，图像处理，自然语言处理，语音识别和合成，图形学，强化学习，用户画像，人机交互和社交心理学。", "虚拟角色研究员：", "结合虚拟偶像项目落地需求，紧密跟踪深度学习各个方向的最新动态，探索可行的算法：", "1. 将深度学习技术应用于人机交互领域，提高用户与虚拟角色的面对面交流体验；", "2. 利用深度学习技术，改善游戏中虚拟人物情感和意图表达能力"], "requir": ["1. 硕士以上学历（或有相当的工作经验），计算机相关专业；", "2. 有深度学习相关项目经验，包括视觉，图像处理，图形学，自然语言处理，语音处理，用户画像或强化学习，多方向经历者优先；", "3. 在人工智能（包括人机交互，多模态融合，视觉，图像，语音，自然语言，图形学等相关方向）会议和期刊发表过优秀论文者优先；", "4. 能熟练使用主流深度学习框架，如tensorflow, mxnet, caffe, Theano, keras等；", "5. 有良好的分析能力及强烈的解决问题的意愿；", "6. 有良好的编程及实践能力；", "7. 有良好的沟通能力和团队意识；", "8. 对虚拟/增强现实有兴趣者优先；"]},
{"name": "Tech Artist (Procedural) - 雷火事业群", "link": "https://hr.163.com/position/detail.do?id=18507", "address": "国外", "cotegory": "雷火事业群", "type": "游戏>游戏程序", "num": "1人", "duty": ["NetEase games is looking for experienced technical artist focusing on procedural generation of large and complex environment, in order to meet the ever growing project scales. Candidates will participate in multiple projects across various platforms. Procedural generation with Houdini, etc and integrating of pipeline into production is the Key to the job.", "Job Responsibilities:", " *  Develop procedural generation tools for various environment components, including terrain, vegetation, buildings and props. ", " *  Integrate procedural tools to art production pipeline and optimize the efficiency.", " *  Manage resources and standards for art asset production related to procedural generation.", " *  Provide supporting and training for artists and junior TA/TD, to help them adapt to new tools and workflows.", " *  Assist artificial intelligence R&D teams on topics related to environment generation."], "requir": [" *  3+ years working as TA/TD in video game industry. Preferred if having shipped AAA titles on major platforms.", " *  Proficiency in developing procedural modeling/generation tools with Houdini or other tools.", " *  Programming with scripting language to develop production pipeline tools, is required. Preferred language is Python.", " *  Programming in game-engine to allow data transfer between generated content and game asset, is required.", " *  Knowledge of realtime 3D render principle, Shader authoring, material and lighting is preferred.", " *  Understanding of performance constraints in game production and able to optimize tools and resource standards to meet requirement of different platform.", " *  Interest and knowledge of climate, geology, biology, architecture, landscape, city planning, etc.", " *  Strong verbal and written communication skills with large teams. ", " *  Fluent in English. Chinese (Mandarin) speaker is a plus.", " *  Willing to travel to China several times per year to communicate with local teams."]},
{"name": "高性能计算工程师-伏羲实验室003", "link": "https://hr.163.com/position/detail.do?id=13125", "address": "杭州市", "cotegory": "伏羲实验室", "type": "技术>人工智能", "num": "1人", "duty": ["具备良好的体系结构知识和系统调优经验，充分挖掘硬件的计算、访存性能，为深度学习的训练及推断过程提供高效的分布式系统。"], "requir": ["1、热爱技术，有创造精神。乐意学习新的知识，并以此对自己和他人带来帮助。", "2、有良好的计算机知识和功底，了解计算机及网络的工作原理：", "         1）高性能基础：熟悉BLAS、Linpack等数学库的工作原理及优化方法", "         2）linux：性能分析，网络监控，具备系统资源虚拟化相关知识", "         3）体系结构：了解并行计算及异构计算", "         4）算法基础：对NLP、CV或强化学习中至少一个方向的相关算法有所了解", "5）网络知识：TCP/IP协议、NAT协议、内网配置管理", "3、编程及实践能力：", "         1）具备基于linux的编程及调试能力", "         2）熟悉python、JAVA或C++等至少一门编程语言", "         3）了解tenserflow、mxnet、pytorch或caffe中至少一种DL平台", "         4）优秀开源项目的使用及阅读经历", "4、加分项：", "         1）熟悉GPU硬件架构，了解NCCL、MPI等编程框架", "       2）开源项目贡献者", "3）熟悉CPU体系结构及优化方法"]},
{"name": "系统研发工程师 - 伏羲实验室003", "link": "https://hr.163.com/position/detail.do?id=16449", "address": "杭州市", "cotegory": "伏羲实验室", "type": "技术>服务端开发", "num": "2人", "duty": ["负责企业生产场景下大规模系统的研发、维护及调优工作。将云计算技术赋能游戏及AI场景。"], "requir": ["1、三年以上研发经验，有大规模系统研发维护经验的优先", "2、扎实的计算机基础知识，熟悉操作系统内核、计算网络及体系结构", "3、具备一定的云计算、分布式存储经验；docker及K8S相关经验优先", "4、良好的性能分析、问题定位能力，可以熟练使用相关分析工具", "5、熟悉Java、C++至少一门开发语言"]},
{"name": "游戏AI产品策划-伏羲实验室005", "link": "https://hr.163.com/position/detail.do?id=10011", "address": "杭州市", "cotegory": "伏羲实验室", "type": "产品>产品策划", "num": "1人", "duty": ["岗位描述: ", "1、结合人工智能技术设计未来游戏概念。", "2、收集并分析游戏AI需求，并提出产品设计方案。", "3、推进产品测试，持续改善产品体验。"], "requir": ["岗位要求：", "1、本科或以上学历。", "2、了解机器学习、深度学习、强化学习常用算法，有图像处理相关专业背景尤佳。", "3、做事认真负责，有耐心，有上进心，乐于接受新事物。", "4、热爱游戏，丰富的游戏体验，善于思考游戏设计意图。", "5、良好的沟通和团队合作能力。"]},
{"name": "AI系统工程师 - 伏羲实验室003", "link": "https://hr.163.com/position/detail.do?id=20279", "address": "杭州市", "cotegory": "伏羲实验室", "type": "技术>服务端开发", "num": "1人", "duty": ["1,负责深度学习应用在端侧的落地与实践,为未来深度学习服务化场景,提供解决方案.", "2,负责深度学习领域前沿问题的探索与研究,利用最新技术解决AI系统及工程化热点问题.", "3,基于AI云平台,构建AI系统能力，扩宽平台业务边界.", "4,理解图像/NLP/强化学习/用户画像等领域算法,紧抓业务特点,推进算法落地."], "requir": ["1, 硕士及以上学历，计算机相关专业.", "2, 有深度学习理论基础,对图像/NLP/强化学习/用户画像其中一个以上方向有充分了解.", "3, 具备极佳的工程实现能力, 熟悉linux, 熟悉C/C++,有python/shell编程基础.", "4, 有发现问题 分析问题 解决问题的能力.", "5, 有团队意识，与他人合作良好."]},
{"name": "自然语言处理工程师 - 伏羲实验室004", "link": "https://hr.163.com/position/detail.do?id=14916", "address": "杭州市", "cotegory": "伏羲实验室", "type": "技术>人工智能", "num": "3人", "duty": ["1、从事与自然语言处理相关产品的研发工作", "2、开发并维护相关平台及工具，提高研发效率", "3、改善现有的自然语言处理相关算法，适用于各类业务"], "requir": ["1、具有机器学习的基础知识，了解常见机器学习算法", "2、具有深度学习的基础知识", "具有自然语言处理(NLP)的基础知识和DL4NLP的相关知识", "3、能够熟练使用主流深度学习框架，如pytorch, tensorflow, keras等", "4、计算机基础知识扎实，熟悉算法数据结构，具有良好的编程能力", "5、有在linux上进行开发的经验，能使用Spark等系统进行海量数据处理", "6、了解、能使用各种数据库软件，如MariaDB，MongoDB，Redis等", "5、参加过各类编程比赛（ACM，蓝桥杯等）并获得过奖项或在各类与自然语言处理技术有关的数据比赛并获得过较好名次或参与过知名开源项目优先", "6、在ACL，EMNLP，NAACL及其他相关会议（AAAI, IJCAI, KDD等）发表过paper优先"]},
{"name": "高级交互设计师 - 伏羲实验室003", "link": "https://hr.163.com/position/detail.do?id=19988", "address": "杭州市", "cotegory": "伏羲实验室", "type": "设计>交互设计", "num": "1人", "duty": ["配合策划、产品经理完成产品交互原型，保证产品流畅、易用；  ", "负责web端、移动端产品的界面设计和交互设计；  ", "深入分析现有产品的界面交互优缺点，提出有效解决方案并优化； ", "负责相关产品的前期产品概念规划、低高保真原型设计以及已有产品的优化； ", "与整个研发团队紧密配合，协助达成最终产品目标。"], "requir": [" 本科以上学历，2年以上交互设计经验，有成熟作品 ; ", "依据核心需求进行功能层面的设计，包含整体架构、用户流程，并以使用场景为依归进行实际设计产出，确保产品功能符合核心需求及用户体验； ", "熟练使用Photoshop、Axure、Sketch等相关软件； ", "掌握一定的设计理论与工具方法； ", "逻辑思维清晰，具备自驱力，具备良好的沟通能力，善于总结，最好具备文字表达能力 ； ", "具备良好合作态度及团队精神，并富有工作激情、创造力和责任感，能承受一定工作压力", "简历请附作品（网页或软件交互设计相关作品）"]},
{"name": "虚拟人算法工程师 - 伏羲实验室004", "link": "https://hr.163.com/position/detail.do?id=20234", "address": "杭州市", "cotegory": "伏羲实验室", "type": "技术>人工智能", "num": "1人", "duty": ["深度参与虚拟人相关算法落地，对真实业务场景负责，融合视觉语音自然语言等多模态，算法与工程并举，提高泛娱乐（游戏，短视频，VTuber等）内容生产效率，创造崭新的交互游戏体验"], "requir": ["- 计算机相关专业硕士及以上学历", "- 扎实的深度学习基础，深度学习，计算机视觉，语音合成，自然语言处理，情感计算，数字媒体技术等专业背景或有相关工作经历；特别的，有语音合成相关项目经历或乐于尝试该方向者优先", "- 优秀的编程能力和良好的编码习惯，动手能力强", "- 熟练使用至少一种编程语言，熟练使用 Python 优先", "- 熟练使用至少一种深度学习框架，包括但不限于 PyTorch，TensorFlow，MXNet，Chainer", "- 良好的沟通表达能力，善于团队合作"]},
{"name": "智能虚拟交互引擎工程师 - 伏羲实验室004", "link": "https://hr.163.com/position/detail.do?id=15895", "address": "杭州市", "cotegory": "伏羲实验室", "type": "技术>服务端开发", "num": "1人", "duty": ["负责融合最新人工智能技术的游戏服务器系统架构设计、模块划分、把控服务器代码品质", "负责实现服务器端关键框架代码，并完成相应的文档", "同产品策划、AI研究员及游戏客户端人员进行有效沟通，分析、解决各种服务器的问题"], "requir": ["-计算机,软件开发,游戏开发,网络安全等本科及以上学历", "-扎实的计算机基础知识,深入理解数据结构,算法,操作系统等知识", "-良好的C++编程功底, 精通一门脚本语言，如python、lua", "-熟悉网络编程与多线程编程,具备较强的代码调试能力", "-追求极致，有丰富的性能优化经验", "-熟悉mysql数据库,熟悉Linux/Unix类操作系统", "-热爱游戏,具有创业激情及创业心态,目标导向,抗压能力强, 具备很好的学习和技术研究应用的能力", "-出色的团队协作能力,善于沟通,敬业专注", "-具备很强的执行力和深度思考的能力", "-具备大型游戏服务器端程序开发经验者优先", "-有人工智能相关项目经验者优先"]},
{"name": "产品运营专员 - 有道事业群706", "link": "https://hr.163.com/position/detail.do?id=20819", "address": "广州市", "cotegory": "有道事业群", "type": "产品>产品运营", "num": "1人", "duty": ["1、\t协助资源洽谈，评估资源价值，负责资源上线，提升资源变现。", "2、\t解决客户投放相关的系统问题，理解用户需求，对竞品进行分析，提出改善产品和用户体验的新方法，并不断尝试和改进。", "3、\t完成有道智选产品运营日常工作支持,包括定时发布的运营数据日报/周报/月报，根据数据后台监控产品运营数据或用户数据的异常情况并分析可能的原因找到解决办法。 ", "4、    了解行业动向，及时、准确地研究、监控、分析竞争对手动态，并提出相应的对策 。"], "requir": ["1、\t本科电子商务、计算机等专业；", "2、\t良好的数据处理能力及逻辑思维能力，熟悉Excel、PPT等常规办公软件；", "3、\t对广告产品设计，对产品分析、数据分析等有见解；", "4、\t工作富有激情，具有较强的主动性和学习意识，考虑问题系统化；", "5、    热爱互联网广告行业，富有激情，具有创新精神，乐于团队协作；"]},
{"name": "资深游戏客户端开发 - 上海-天下事业部400", "link": "https://hr.163.com/position/detail.do?id=16896", "address": "上海市", "cotegory": "互动娱乐事业群", "type": "技术>研发类", "num": "2人", "duty": ["职位描述： ", "- 负责动作手游客户端程序开发； ", "- 根据需求实现游戏的战斗/场景/系统/界面等效果；   ", "- 对项目存在的性能问题定位和优化。 "], "requir": ["任职资格： ", "- 个人综合能力突出，有培养和成长为骨干程序的潜力（核心要求） ", "- 优秀的学习和沟通能力，并热爱游戏事业； ", "- 熟悉C/C++；熟悉算法和数据结构； ", "- 本科以上学历； ", "- 熟练使用Python/Lua者优先； ", "- 有3D游戏开发经验者优先； ", "- 有Unity3D或Cocos2D开发经验者优先； ", "- 有PC动作游戏网游开发经验者优先；  ", "- 三年左右的商业化网络游戏开发经验，兼具运营维护经验者更佳 "]},
{"name": "制作人 - 梦幻事业部700", "link": "https://hr.163.com/position/detail.do?id=20341", "address": "广州市", "cotegory": "互动娱乐事业群", "type": "策划>制作人", "num": "1人", "duty": ["负责某一方向题材的手游产品设计工作。", "负责产品最终品质的把控。"], "requir": ["本科及以上学历；", "经历过完整的手游项目研发经验，从立项，研发，到上线运营整个生命周期的工作。", "对某一个方向题材的手游有丰富的体验和设计经验。", "有成功手游的研发和运营经验优先考虑。"]},
{"name": "游戏客户端开发-杭州-天下事业部400", "link": "https://hr.163.com/position/detail.do?id=14674", "address": "杭州市", "cotegory": "互动娱乐事业群", "type": "技术>研发类", "num": "3人", "duty": ["职位描述：", "- 负责动作手游客户端或服务器程序开发；", "- 根据需求实现游戏的战斗/场景/系统/界面等效果；", "- 对项目存在的性能问题定位和优化。"], "requir": ["任职资格：", "- 个人综合能力突出，有培养和成长为骨干程序的潜力（核心要求）", "- 优秀的学习和沟通能力，并热爱游戏事业；", "- 熟悉C/C++；熟悉算法和数据结构；", "- 本科以上学历；", "- 熟练使用Python/Lua者优先；", "- 有3D游戏开发经验者优先；", "- 有Unity3D或Cocos2D开发经验者优先；", "- 有PC动作游戏网游开发经验者优先；", "- 三年以内的商业化网络游戏开发经验，兼具运营维护经验者更佳"]},
{"name": "Web前端开发工程师-伏羲实验室003", "link": "https://hr.163.com/position/detail.do?id=7766", "address": "杭州市", "cotegory": "伏羲实验室", "type": "技术>前端及客户端开发", "num": "2人", "duty": ["1.负责前端页面的设计、开发、维护工作", "2.负责数据可视化效果的实现", "3.负责与后端开发人员协调沟通，高效完成页面"], "requir": ["1.计算机及相关专业本科以上学历，3年以上Web前端开发经验", "2.熟练掌握HTML5、CSS3、JavaScript、ES6", "3.能熟练掌握至少一种主流前端框架Vue、Angular、React等，并了解其原理", "4.熟悉前端构建工具，如Webpack、Gulp等", "5.熟悉Linux系统下的开发环境，了解一门服务端(Python/PHP等)语言", "6.对掌握JS数据可视化技术（如D3、Highcharts）优先", "7.具备良好的学习能力和沟通能力，富有责任心"]},
{"name": "Art Director (Montreal) - 雷火事业群", "link": "https://hr.163.com/position/detail.do?id=18066", "address": "国外", "cotegory": "雷火事业群", "type": "游戏>游戏美术", "num": "1人", "duty": ["NetEase Games Montreal is the brand new division of NetEase Games; a leading game developer and publisher focusing on delivering top quality mobile and online gaming experiences. We’re currently seeking Art Director for our next AAA project to provide artistic direction for the character team. ", "Job Responsibilities:", "•Develop the artistic direction for characters of the game following the storyline;", "•Define the visual design principles for concept artists to achieve unique and unified style for character design;", "•Elaborate the visual references of the artistic direction that will be used as a guide for the artistic team regarding the required quality standards;", "•Collaborate with the animators, programmers and game designers to optimize the visual needs while respecting everyone’s constraints;", "•Demonstration of a concept’s evolution from rough ideation to final result;", "•Divide the tasks efficiently within the artistic conception team;"], "requir": ["•Passionate about video games, with a strong interest in photorealistic/cinematic styles;", "•A minimum of 6 years’ experience as a Concept or 3D Artist;", "•At least 2 as an Artistic Director;", "•Minimum of 2 published titles;", "•Experience in creating original intellectual properties in a video game context;", "•Mastery of versatile 2D and 3D applications;", "•Experienced in working with game engines;", "•Ability to adapt work for marketing needs and supervise production;", "•Excellent innovation skills and excellent understanding of the creative process;", "•Excellent communication skills and ability to visualize and communicate ideas;", "Other Requirements", "Portfolio/Demo Reel", "Referrals (optional)"]},
{"name": "高级/资深游戏客户端开发-上海-天下事业部140", "link": "https://hr.163.com/position/detail.do?id=14685", "address": "上海市", "cotegory": "互动娱乐事业群", "type": "技术>研发类", "num": "3人", "duty": ["次世代足球新项目、非对称竞技新项目、次世代3D开放世界MMO、新沙盒，几个项目（均同一自研引擎）", " ", "职位描述：   ", "- 负责动作手游客户端或服务器程序开发；", "- 根据需求实现游戏的战斗/场景/系统/界面等效果； ", "- 对项目存在的性能问题定位和优化。"], "requir": ["任职资格：", "- 个人综合能力突出，有培养和成长为骨干程序的潜力（核心要求）  ", "- 优秀的学习和沟通能力，并热爱游戏事业；", "- 熟悉C/C++；熟悉算法和数据结构；", "- 本科以上学历；", "- 熟练使用Python/Lua者优先；", "- 有3D游戏开发经验者优先；", "- 有Unity3D或Cocos2D开发经验者优先；", "- 有PC动作游戏网游开发经验者优先；", "- 三年以内的商业化网络游戏开发经验，兼具运营维护经验者更佳"]},
{"name": "算法教研实习生", "link": "https://hr.163.com/position/detail.do?id=14274", "address": "北京市", "cotegory": null, "type": "教育>教育", "num": "1人", "duty": ["1、负责信息学、ACM算法题目挖掘、算法设计、测试点编写；", "2、配合课程体系，对算法题目进行分类、打标签工作；", "3、参与教研团队算法设计与教研工作。"], "requir": ["1、本科及以上学历，计算机相关专业；", "2、掌握C、C++语言；", "3、了解基本的数据结构和算法；", "4、逻辑清晰，思维敏捷，有责任感和内容品质追求；", "5、学习能力强，能主动学习新技术者优先；"]},
{"name": "Senior Character Rigger - 雷火事业群812", "link": "https://hr.163.com/position/detail.do?id=20627", "address": "国外", "cotegory": null, "type": "游戏>游戏美术", "num": "1人", "duty": ["Job Description", "NetEase Games Montreal is the brand new division of NetEase Games; a leading game developer and publisher focusing on delivering top quality mobile and online gaming experiences. We’re currently seeking Character Rigger who will be supporting and improving the level of realism in the character deformation.  Working closely with Animation team and Modeling team the character Rigger will handle animation rigs and other dynamic system.", "Job Responsibilities", "* Create and update animation rig that allow a realistic mesh deformation base on movement.", "* Build automated animation systems for all the secondary motion object, rigid body, cloth, hair etc.     ", "* Collaborate whit animation and character team to provide rigging solution that allow the best quality respecting constrain (time, budget, naming convention etc.)"], "requir": ["Qualifications", "* At least 5 years’ experience in 3D animation.", "* Minimum of 1 published AAA title.", "* Versatile and exceptional skills in 3D animation.", "* Rigging/skinning/weighting skills.", "* Expert in 3D software such as Maya, Motion Builder and 3DS Max.", "* Experience and understanding of character and animation pipelines and character setup.", "* Experienced in working with game engines.", "* Experience creating menus in UMG of UE4 is a plus.", "Other Requirements", "Portfolio"]},
{"name": "web后端开发工程师-伏羲实验室003", "link": "https://hr.163.com/position/detail.do?id=7925", "address": "杭州市", "cotegory": "伏羲实验室", "type": "技术>服务端开发", "num": "5人", "duty": ["负责游戏ai部门系统的后端开发、维护工作；", "负责web系统分析、优化与架构工作；"], "requir": ["1.   熟练掌握Python、PHP等web后端开发语言，熟练使用主流web开发框架（例如flask，django；", "2.   熟悉Linux开发环境；", "3.   熟练使用MySQL，有设计数据表的经验；", "4.   能独立配置Apache、nginx服务器；", "5.   有丰富web后端系统性能调优经验；", "6.   1 年以上工作经验，有丰富游戏经验优先；"]},
{"name": "VFX Specialist (Montreal) - 雷火事业群", "link": "https://hr.163.com/position/detail.do?id=18080", "address": "国外", "cotegory": "雷火事业群", "type": "游戏>游戏程序", "num": "1人", "duty": ["NetEase Games is looking for skilled and experienced effect technical artist. The role would focus on developing workflows for effects that is technically atypical or complicated. And collaborate with other team members to develop mechanics that better connects visual effect and gameplay. Candidates will participate in various projects for current and next generation platforms, both desktop and mobile. ", "Job Responsibilities:", " *  Integrate new technology and tricks into existing workflow to allow more complex and visually stunning effects.", " *  Work with programmers, artists and designers to develop effect pipeline that resonate better with gameplay mechanics.", " *  Design principles and regulations of managing shader/code/art resources across multiple projects. ", " *  Provide supporting and training for artist and junior TA/TD, to help them adapt to new tools and workflows."], "requir": ["Qualifications:", " *  3+ years working as effect artist/TD in video game industry. Preferred if having shipped AAA titles on major platforms.", " *  Proficiency in authoring effects with in-game tools, such as Unity, Unreal, etc.", " *  Familiar with procedural/simulation techniques in Maya/Houdini/Real Flow etc, and have experience integrating them into game effect production.", " *  Programming and tool development with script language in content creation tools is required, such as Python, HScript, VEX and MEL.", " *  Shader writing with HLSL, GLSL, Cg, etc, is required.", " *  Ability to program in game engine and create effect mechanics, is a plus.", " *  Strong verbal and written communication skills with large teams. ", " *  Fluent in English. Chinese (Mandarin) speaker is a plus.", " *  Willing to travel to China several times per year to communicate with local teams.", "Other Requirements", "Portfolio"]},
{"name": "资深技术美术工程师 - 伏羲实验室002", "link": "https://hr.163.com/position/detail.do?id=18890", "address": "杭州市", "cotegory": "伏羲实验室", "type": "游戏>游戏程序", "num": "1人", "duty": ["  ● 【工程落地】在美术工具或游戏引擎中开发可以提升生产效率和表现效果的辅助工具", "  ● 【虚拟人表现】对3D图形渲染和图形学有基本认识，能完成各类模型的渲染支持，了解最前沿渲染的技术。了解虚拟人建模，绑定，材质等方面更佳", "  ● 【算法及数据优化】基于对动画表现的深度理解，以技术美术的理论，参与虚拟人表现的算法开发", "  ● 【美术管理】作为程序和美术之间的沟通桥梁，制定AI虚拟人研发过程美术需求和工作流程"], "requir": ["  ● 具有美术基础，对形式、色彩、光影、动态有比较明确的认识和敏锐的辨识能力；", "  ● 熟悉美术制作工具的使用，比如3ds max，maya，photoshop，zbrush，至少能熟练使用一种3D制作软件max/maya/c4d/blender等", "  ● 了解编程原理和程序基本结构，会使用如python，c#，java，lua类型的语言，或maxscript，MEL等软件工具内建二次开发语言；", "  ● 熟悉unity或unreal Engine等任意一款商业引擎", "  ● 强烈的求知欲和优秀的学习能力，认可算法对于交互式虚拟人的深远价值", "  ● 良好的团队协作精神和沟通能力"]},
{"name": "Senior Engine Programmer (Montreal) - 雷火事业群", "link": "https://hr.163.com/position/detail.do?id=18079", "address": "国外", "cotegory": "雷火事业群", "type": "游戏>游戏程序", "num": "1人", "duty": ["NetEase Games Montreal is the brand new division of NetEase Games; a leading game developer and publisher focusing on delivering top quality mobile and online gaming experiences. We’re currently looking for Senior Engine Programmer for our next AAA console project to defining overall architecture and implementing low-level systems that meet the requirements of the project’s design and technical requirement of target platform.", "Job Responsibilities:", "•\tWork on multiple platforms and on low-level topics, such as: memory management, file system, platform-specific features;", "•\tAnalyze and understand the requirements of the game teams, in order to assess their technical feasibility, define and then implement the required features; ", "•\tImproving the existing pipeline that match the project’s needs;", "•\tAnalyze code performance and optimize whenever needed;", "•\tHelp to determine CPU and memory budgets;"], "requir": ["Qualifications:", "•\t6+ years game engine development experience;", "•\tMinimum of 1 published AAA title;", "•\tExcellent C++ proficiency;", "•\tExperience with multiplatform development;", "•\tExperience with multithreading;", "•\tExcellent understanding of CPU and GPU bottlenecks;", "•\tGood experience with optimizations", "•\tConsole development (PS4 and/or XBox1) is mandatory;", "•\tExperience with Unreal Engine and Unity3D is a plus;"]},
{"name": "用户画像工程师-伏羲实验室003", "link": "https://hr.163.com/position/detail.do?id=7618", "address": "杭州市", "cotegory": "伏羲实验室", "type": "技术>数据分析与管理", "num": "2人", "duty": ["1.\t从事游戏相关的用户画像及推荐系统研发工作；", "2.\t开发并维护相关平台及工具，提升运营效率及用户体验；"], "requir": ["1.\t有一定的游戏经历，热爱人工智能；", "2.\t计算机或相关专业硕士以上学历，扎实的机器学习及用户画像基础；", "3.\t能熟练使用主流深度学习框架，如tensorflow、mxnet、caffe、theano、keras等；", "4.\t有在Linux上处理海量数据的丰富经验，能使用Hadoop、CDH、Spark系统进行海量数据处理、并完成性能调优；", "5.\t有丰富的分布式系统、MPP系统的设计、使用经验；", "6.\t编程基础扎实，熟悉算法数据结构，有丰富的开发调试经验；", "7.\t专注，精益求精，有良好的分析能力及强烈的解决问题的意愿；"]},
{"name": " Senior Animator(Montreal) - 雷火事业群", "link": "https://hr.163.com/position/detail.do?id=18077", "address": "国外", "cotegory": "雷火事业群", "type": "游戏>游戏美术", "num": "1人", "duty": ["NetEase Games Montreal is the brand new division of NetEase Games; a leading game developer and publisher focusing on delivering top quality mobile and online gaming experiences. We’re currently seeking Senior Animator who will work closely with the Animation Director to maintain and create high quality animations for real time game movement to support gameplay.", "Job Responsibilities:", "•\tSkillset to create high quality animation assets for AAA Games;", "•\tFit the style and aesthetic of the game;", "•\tMaintain the movement style of the game and character personalities;", "•\tGood communication skills to both fellow team members & other departments;"], "requir": ["Qualifications:", "•\tAt least 5 years’ experience in 3D animation;", "•\tMinimum of 1 published AAA title;", "•\tVersatile and exceptional skills in 3D animation;", "•\tProven excellence in realistic hand keyed and mocap animation;", "•\tExpert in Animation software such as Maya, Motion Builder and 3DS Max;", "•\tExperience and understanding of character and animation pipelines and character setup;", "•\tExperienced in working with game engines;", "•\tExperience creating menus in UMG of UE4 is a plus.", "Other Requirements", "Portfolio"]},
{"name": "Senior Gameplay Programmer-3C (Montreal) - 雷火事业群", "link": "https://hr.163.com/position/detail.do?id=18081", "address": "国外", "cotegory": "雷火事业群", "type": "游戏>游戏程序", "num": "1人", "duty": ["Job Description", "NetEase Games Montreal is the brand new division of NetEase Games; a leading game developer and publisher focusing on delivering top quality mobile and online gaming experiences. We’re currently looking for Senior Gameplay Programmer with 3C related experience for our next AAA project to work closely with game designers to design, explore, and implement various gameplay features.", "Job Responsibilities:", "•\tResponsible for 3C aspect of gameplay programming from invention and prototyping to full implementation;", "•\tWrite clear, optimized, modularized code that is suitable for continuous integration and continuous deployment which respects best practices and software guidelines; ", "•\tCollaborate with the team to design and architect major gameplay systems;", "•\tGood communicate with artists and designers;", "•\tCapable of quick iteration and feedback loops while working with the team."], "requir": ["Qualifications:", "•\t6+ years 3C related gameplay development experience;", "•\tMinimum of 1 published AAA FPS title;", "•\tExcellent C++ proficiency;", "•\tExcellent architecture and system design ability;", "•\tExperience in the design and implementation of character control systems, animation system, weapons, skills etc.", "•\tExperience with multi-threaded programming paradigms;", "•\tExperience with Unreal Engine and Multiplayer architecture is a plus;"]},
{"name": "Lead Level Designer (Montreal)   - 雷火事业群", "link": "https://hr.163.com/position/detail.do?id=18069", "address": "国外", "cotegory": "雷火事业群", "type": "游戏>游戏策划", "num": "1人", "duty": ["NetEase Games Montreal is the brand new division of NetEase Games; a leading game developer and publisher focusing on delivering top quality mobile and online gaming experiences. We’re currently looking for Senior Level Designer for our next AAA project to manage the creation and implementation of all design content and ensure that its gameplay reflects the vision of the game and fully exploits its given mechanics.", "Job Responsibilities:", "•\tMentor level designers and provide example of guidelines within the project;", "•\tCreate quality goals, workflows and guides for all game relevant content elements;", "•\tCollaborate with all development disciplines to shepherd various level design constructs through the iterative process, from inception to final;", "•\tCreate quality goals, workflows and guides for all game relevant content elements;", "•\tWork closely with level artist, and game design teams to ensure game areas meet established art and design goals;", "•\tReview levels and provide constructive feedback to fellow level designers to help improve the quality;"], "requir": ["Qualifications:", "•\t5+ years level design experience;", "•\tMinimum of 1 published title;", "•\tStrong ability to learn and master new tools and techniques;", "•\tExtensive understanding of design processes including game design, level design, content design and game writing;", "•\tExperience in 3D software such as; Sketchup, 3dsMax and Maya;", "•\tExcellent communication and documentation skills;", "•\tExperienced in working with game engines;", "•\tExperienced in UE4 is a plus.", "Other Requirements", "Portfolio"]},
{"name": "Senior Concept Artist(Montreal) - 雷火事业群", "link": "https://hr.163.com/position/detail.do?id=18078", "address": "国外", "cotegory": "雷火事业群", "type": "游戏>游戏美术", "num": "2人", "duty": ["NetEase Games Montreal is the brand new division of NetEase Games; a leading game developer and publisher focusing on delivering top quality mobile and online gaming experiences. We’re currently seeking Senior Concept Artist for our next AAA project to create original and imaginative concept art for characters. ", "Job Responsibilities:", "•\tWork closely with the Art Director and Game Designer to take creative direction as well as reinforce the execution of the game’s visual design;", "•\tCollaborate with other artists to create the character design of the game;", "•\tContribute innovative and original ideas toward all aspects of the game’s production and development;", "•\tStrong work ethic, self-direction and artistic vision, dedicated work ethic;", "•\tAccept and provide direction with team members and participate and engage with the entire production team to stay current on the scope and understanding of the project;"], "requir": ["Qualifications:", "•\tKnowledge of art history and contemporary culture;", "•\tA minimum of 3 years’ experience as a Concept Artist;", "•\tMinimum of 1 published title;", "•\tExpert of 2D applications;", "•\tExperienced in working with game engines;", "•\tExcellent knowledge of human anatomy and proportions is a plus ", "Other Requirements", "Portfolio"]},
{"name": "Senior Render Programmer(Montreal) - 雷火事业群", "link": "https://hr.163.com/position/detail.do?id=18310", "address": "国外", "cotegory": "雷火事业群", "type": "游戏>游戏程序", "num": "1人", "duty": ["Job Description", "NetEase Games Montreal is the brand new division of NetEase Games; a leading game developer and publisher focusing on delivering top quality mobile and online gaming experiences. We’re currently looking for Senior Render Programmer to craft advanced rendering technology for our next AAA console project.", "Job Responsibilities:", "•\tIn collaboration with artists, tech and design, you will be responsible for implementing, optimizing and maintaining rendering features;", "•\tAnalyze and understand the requirements of the game teams, in order to assess their technical feasibility, define and then implement the required features; ", "•\tImproving the existing pipeline that match the project’s needs;", "•\tAnalyze code performance and optimize whenever needed;"], "requir": ["Qualifications:", "•\t6+ years game engine development experience;", "•\tMinimum of 1 published AAA Console title;", "•\tExcellent C++ proficiency;", "•\tExperience with multiplatform development;", "•\tStrong knowledge of several real-time rendering topics (lighting, shading, shadows, global illumination, post-processing, etc.);", "•\tKnowledge of Graphics APIs (DirectX 11/12, Consoles) and Graphics Pipelines;", "•\tGood experience with optimizations", "•\tStrong knowledge of PC, SONY Playstation 4 and Microsoft XboxOne development;", "•\tExperience with Unreal Engine and Unity3D is a plus;"]},
{"name": "Senior Sound Programmer (Montreal)  - 雷火事业群", "link": "https://hr.163.com/position/detail.do?id=18068", "address": "国外", "cotegory": null, "type": "游戏>游戏程序", "num": "1人", "duty": ["NetEase Games Montreal is the brand new division of NetEase Games; a leading game developer and publisher focusing on delivering top quality mobile and online gaming experiences. We’re currently looking for Senior Sound Programmer to develop state-of-the-art audio solutions for our next AAA project.", "Job Responsibilities:", "•\tImplement new and/or maintain existing groundbreaking audio capabilities;", "•\tDesign, develop and/or support existing in-house audio tools and low level audio code;", "•\tFeature addition and improvement based on project and studio needs;", "•\tSupport and actively collaborate with other team members;", "•\tAudio code optimization to fit target platform technical limitations;"], "requir": ["•\t5+ years gameplay development experience;", "•\tMinimum of 1 published title;", "•\tExcellent C/C++ proficiency;", "•\tComfortable writing and maintaining audio systems at all levels, from the base audio engine to game code, music and dialog management and tool support;", "•\tExperience with middleware audio solutions;", "•\tAble to communicate effectively and actively;"]},
{"name": "语音合成研究员-伏羲实验室004", "link": "https://hr.163.com/position/detail.do?id=7823", "address": "杭州市", "cotegory": "伏羲实验室", "type": "技术>人工智能", "num": "6人", "duty": ["- 负责语音合成相关算法的实验开发和产品化落地", "- 追踪语音合成方向的前沿研究，改进现有方法，撰写论文专利"], "requir": ["岗位要求", "- 计算机/数学/语音/人工智能相关专业，研究生及以上学历", "- 扎实的机器学习/深度学习基础，熟悉基本方法论和经典算法", "- 熟练使用至少一种深度学习框架，包括但不限于 PyTorch/TensorFlow/MXNet", "- 在语音或深度学习顶会或期刊上发表过文章", "加分项", "- 有语音识别/语音合成/语音合成前端/语音信号处理/自然语言处理相关专业背景，从事过相关工作，熟悉 Tacotron2/WaveNet", "- 熟悉生成模型，包括但不限于 GAN/VAE/Glow"]},
{"name": "大客户销售经理 - 政企方向 - 有道事业群704", "link": "https://hr.163.com/position/detail.do?id=20070", "address": "北京市", "cotegory": null, "type": "销售>销售", "num": "1人", "duty": ["1. 负责公司产品及方案在政府、企事业等大客户市场开拓与销售工作，执行并完成各项销售指标；", "2. 维护并发展与目标客户的良好关系，挖掘客户需求，积极推进，为客户提供有效且增值的产品及解决方案；", "3. 开发新客户，开拓销售市场；", "4. 积极主动与各部门配合，完成个人及团队的销售目标。"], "requir": ["1. 计算机通讯类或市场营销类相关专业毕业，本科及以上学历", "2. 具有政府部委/企业/金融/银行/保险/证券/传媒/物流/等行业工作经验，有IT产品的销售工作经验和成功案例", "3. 具备出色的沟通能力，销售技巧、商务谈判能力", "4. 学习能力强，诚信，具有较强的组织、沟通、协调能力及良好的团队合作精神", "5. 工作中具有较强的主动性、积极性与创造性，善于利用各种资源和销售方法取得成效"]},
{"name": "深度学习图像研究员 - 伏羲实验室004", "link": "https://hr.163.com/position/detail.do?id=14968", "address": "杭州市", "cotegory": "伏羲实验室", "type": "技术>人工智能", "num": "3人", "duty": ["1、负责计算机视觉/图形学相关核心技术在游戏相关领域的算法与产品化等研究工作，包括但不限于如下方向：目标追踪，目标检测，图像分割，图像分类，图像/动画生成，三维重建，渲染，蒙皮等。", "2、跟踪学术界和业界最新进展，并且能够快速应用到业务中；", "3、进行技术分享、专利申请和学术文章发表，提高网易伏羲实验室在计算机视觉/图形学领域的的技术影响力。"], "requir": ["1、图像处理、模式识别、计算机视觉、计算机图形学、机器学习等相关专业硕士及以上；", "2、熟悉计算机视觉或图形学领域的主流模型和算法，关注领域内的最新进展；", "3、较强的算法实现能力，熟练掌握C/C++，Python，Java等至少一门语言；熟悉Linux环境开发；", "4、熟练使用一种或几种深度学习框架（caffe，tensorflow，Pytorch等），熟悉OpenCV等常用库；", "5、有较强的研究能力，如在相关领域顶级会议如CVPR，ICCV，ECCV，NIPS，SIGGRAPH等发表过高质量论文者优先；", "6、有ACM相关比赛经验或者在计算机视觉重要数据集（如ImageNet、COCO等）的Leaderboard上排名靠前者优先。", "7、有目标跟踪、目标检测、语义分割、三维重建等实际应用经验者优先。", "8、有良好的团队合作和沟通能力。"]},
{"name": "资深测试工程师-伏羲实验室003", "link": "https://hr.163.com/position/detail.do?id=9870", "address": "杭州市", "cotegory": "伏羲实验室", "type": "技术>测试", "num": "1人", "duty": ["1.         负责人工智能实验室的产品的测试工作，参与互联网软件产品测试的全流程，包括参与需求分析、设计评审、制定测试计划，执行测试用例，测试回归，进行缺陷跟踪和软件质量分析等； ", "2.         通过研发的方式来保障和提升质量，努力提升研发的质量和效率；"], "requir": ["1.         计算机相关专业，本科及以上学历，三年以上开发或者测试开发工作经验；", "2.         精通主流软件测试方法与测试工具，熟悉前沿测试理论方法；", "3.         有丰富的性能、白盒测试的经验；", "4.         熟悉Linux/Unix，掌握Python/Shell等至少一门脚本语言；", "5.         具备丰富的Web测试技术开发经验(React/H5)，能熟练运用业界常见的研发测试工具（如Selenium/Appium等）；", "6.         熟悉相关配置管理、研发管理等工具，如git，sonra，jenkins等；", "7.         参与过大型系统的自动化和性能测试者优先；", "8.         具备良好的沟通协调和团队协作能力，有强烈的责任心和积极主动的工作态度；"]},
{"name": "Senior Tool Programmer(Montreal) - 雷火事业群", "link": "https://hr.163.com/position/detail.do?id=18311", "address": "国外", "cotegory": "雷火事业群", "type": "游戏>游戏程序", "num": "3人", "duty": ["Job Description", "NetEase Games Montreal is the brand new division of NetEase Games; a leading game developer and publisher focusing on delivering top quality mobile and online gaming experiences. We’re currently looking for Senior Tool Programmer to create and improve game development toolsets for our next AAA console project.", "Job Responsibilities:", "•\tWork side by side with designers, artists, and engineers, to design, implement, and iterate data editing tools to allow for efficient, accurate game system data editing and creation;", "•\tExtend existing editors to provide new or improved workflow for team to accomplish their tasks and streamline the process of creating the game; ", "•\tSupport the team with any standalone tools and scripts to facilitate game development, build process, as well as streamline the team’s development environment;"], "requir": ["Qualifications:", "•\t6+ years game engine development experience;", "•\tMinimum of 1 published AAA Console title;", "•\tExcellent C++/C# proficiency;", "•\tAbility to analyze designer/art tool requests and iterate with them to deliver robust and performant tools to help them accomplish their goals;", "•\tExperience with common UI development frame work such as Winforms and WPF;", "•\tExperience with continuous integration, package versioning and distribution", "•\tExperience with Unreal Engine 4 or Unity3D is a plus;"]},
{"name": "Senior Tech Animator (Montreal) -雷火事业群", "link": "https://hr.163.com/position/detail.do?id=18045", "address": "国外", "cotegory": "雷火事业群", "type": "游戏>游戏程序", "num": "2人", "duty": ["NetEase Games is looking for skilled technical animators to develop current and future titles. The role would focus on developing animation pipeline and workflow, providing direction and inputs that would bring cutting-edge technology that would fit the requirement of our projects.", "Responsibilities:", " *Bring cutting-edge technology to the animation production pipeline to improve efficiency and quality, from content creation to final presentation.", " *Design key principles of managing animation tools and resources, improving sharing across multiple projects.", " *Collaborate closely with animation and other teams, creating and supporting tools/rigs.", " * Provide supporting and training for artists and junior TA/TD, to help them adapt to new tools and workflows.", " *Assist artificial intelligence R&D department on topics related to animation."], "requir": [" * 3+ years working as technical animator in the game industry, experience of shipping AAA titles is a plus.", " * Proficiency in one or more animation content production tools, such as Maya, MotionBuilder, 3dsmax, etc.", " * Programming and tool development in one or more DCC script language is required, such as MEL, MaxScript and Python. ", " * Skills of game engine programming and procedural animation is a definite plus.", " * Knowledge of human anatomy and animation principles. Able to create both body and facial rig.", " * Experience in motion capture and cinematics production is a plus.", " * Strong verbal and written communication skills with large teams. ", " * Fluent in English. Chinese (Mandarin) speaker is a plus.", " *Willing to travel to China several times per year to communicate with local teams."]},
{"name": "高级产品经理（少儿英语） - 有道事业部036", "link": "https://hr.163.com/position/detail.do?id=16887", "address": "北京市", "cotegory": null, "type": "产品>产品综合", "num": "1人", "duty": ["1、负责有道3-8岁早期教育相关产品的工作；", "2、挖掘用户的需求，不断优化迭代产品；", "3、思考产品策略，规划产品发展方案；"], "requir": ["1、三年以上的互联网产品项目经验；", "2、有k12或教育行业产品的经验；", "3、有较强的交互设计能力。", "4、做事有高的标准和要求。", "5、有较高的工作热情，保证高的产品质量。"]},
{"name": "游戏测评工程师 - 广州 - 用户体验中心", "link": "https://hr.163.com/position/detail.do?id=20807", "address": "广州市", "cotegory": "互动娱乐事业群", "type": "用户体验>测评类", "num": "6人", "duty": ["•\t从游戏本源和用户需求出发，立足于领先的游戏视野、思维及知识储备，为公司提供多角度的战略及决策支持； ", "•\t深度参与游戏开发，专业分析测评游戏核心系统，为产品完善优化游戏设计提供指标性的参考依据.客观，准确的分析各类网游的品质质量，消除游戏设计隐患，提升游戏品质； ", "•\t客观、准确地分析市场及行业动态，深度研究和剖析游戏设计，提炼出可落地性的方法论和知识体系；", "•\t深度体验游戏，探索游戏深层奥秘，工作娱乐化，娱乐专业化。"], "requir": ["•\t热爱游戏，痴迷游戏，游戏经验丰富，游戏面广泛，真正的游戏爱好者，对自己擅长的游戏有深厚的游理解与强大的游戏实战能力；（游戏经验10年以上，日均游戏体验时间6小时以上）", "•\t男女不限，对游戏的感性体验能够清晰描述，并转化为理性分析；", "•\t性格活泼，善于沟通，具备团队配合能力，懂得如何协作，快速定位自身并融入团队，能够带动团队气氛；", "•\t积极、乐观，抗压性强，低调务实，能够接受加班工作。 ", "以下优势会优先考虑：（排序不分先后） ", "•\t在省级或以上程度的比赛中获得过名次或奖项，有职业玩家背景；   ", "•\t精通市面上各类竞技游戏，高段位者优先；     ", "•\t精通steam、switch、ps4、xbox，WiiU等平台游戏，数量高，时间长者优先；   ", "•\t精通MMO游戏，有深度付费经历，有PVP、PVE、生活等高成就者优先；     ", "•\t精通SLG手游，如率土之滨、三国志战略版等，有高战盟PVP指挥经验，精通策略对抗技巧；     ", "•\t女性向游戏专家，熟知剧情类、文字类、换装类游戏产品的乐趣来源。"]},
{"name": "高级Java开发工程师（内容安全） - 音乐事业部", "link": "https://hr.163.com/position/detail.do?id=20773", "address": "杭州市", "cotegory": "音乐事业部", "type": "技术>服务端开发", "num": "2人", "duty": ["1、基于复杂的业务体系，搭建高并发、高性能、高可用的中台化安全风控服务。", "2、基于海量数据构建安全数仓，为在线和离线安全服务提供数据支持，以识别恶意用户、机器行为等。", "3、解决海量数据实时及离线处理中遇到的难题，保证系统的鲁棒性、高可用。", "4、参与安全工程体系能力建设"], "requir": ["1、本科及以上学历，计算机、数学、统计学等相关专业。", "2、熟练掌握Java/Spring等，能独立完成项目工程建设。", "3、熟悉大数据主流开源组件（Hadoop/Hive/Spark/Flink等），并了解其特性和使用场景。", "4、熟练使用Java/python/Scala/sql等完成数据分析、算法开发任务优先。", "5、有数仓开发、数据挖掘、机器学习相关工作经验优先。", "6、有业务风控、反爬、内容反垃圾等安全相关工作经验优先。", "7、具备良好的学习能力、分析和解决问题的能力。", "8、具备良好的沟通能力及团队协作精神，对工作积极严谨，勇于承担压力。"]},
{"name": "游戏编辑器策划（平安京项目） - 大话事业部700", "link": "https://hr.163.com/position/detail.do?id=20592", "address": "广州市", "cotegory": null, "type": "策划>系统策划", "num": "1人", "duty": ["1、负责游戏编辑器现有功能的更新和新功能的设计； ", "2、负责游戏编辑器平台的运营和维护； ", "3、负责与游戏平台作者和玩家群体的沟通和维护，挖掘作者的需求； ", "4、负责游戏编辑器和平台的发展规划。"], "requir": ["1、有《决战！平安京》Uni编辑器做图经验优先，请在简历附上你的昵称、作品名字和玩法介绍； ", "2、能够深入研究游戏编辑器的底层功能，可以提出有建设性的建议； ", "3、热衷游戏制作，有良好的团队协作能力、抗压能力、沟通能力，学习能力强，思维跃、逻辑清晰； ", "4、需要逻辑性强，有基础的编程能力；", "5、计算机软件相关专业优先。"]},
{"name": "服务端开发工程师 - 有道事业群704", "link": "https://hr.163.com/position/detail.do?id=20808", "address": "北京市", "cotegory": null, "type": "技术>服务端开发", "num": "2人", "duty": ["1，负责有道词典项目及相关产品的服务器端开发。", "2，负责已有产品的代码优化和新产品的技术调研、实现。"], "requir": ["1，计算机以及相关专业本科以上学历。", "2，三年以上 Java 编程经验 ，了解C++/Python等编程语言。", "3，熟悉 Linux 系统，能够在 Linux 环境下进行开发。", "4，熟悉计算机网络，熟悉 HTTP 协议，熟悉 Web 应用开发技术，对服务性能有极致追求。", "5，熟悉数据库相关技术，熟悉Redis、MongoDB、Cassandra等NoSQL使用经验优先。", "6，具有良好而规范的编程习惯和技术文档编写习惯。"]},
{"name": "UU加速器产品运营实习生-数据运营 - 游戏应用与平台发展事业部002", "link": "https://hr.163.com/position/detail.do?id=20809", "address": "广州市", "cotegory": null, "type": "运营>运营类", "num": "1人", "duty": ["1.协助分析指标数据，并提供优化建议", "2.协助商业化研究，以及活动运营的跟进", "3.协助研究用户生命周期，并搭建有效运营模式"], "requir": ["1.熟悉运用SQL语言", "2.逻辑思维能力强，有很好的数据分析能力", "3.对不同的产品形态有一定的了解和接触", "4.具有创新意识，执行能力和沟通能力强", "5.至少实习4个月，每周保证4天到岗，周末除外"]},
{"name": "高级Java开发工程师（音乐人平台） - 音乐事业部002", "link": "https://hr.163.com/position/detail.do?id=20778", "address": "杭州市", "cotegory": "音乐事业部", "type": "技术>服务端开发", "num": "2人", "duty": ["1、参与原创音乐平台服务端功能模块设计、开发、编码、测试以及文档编写等工作；", "2、参与原创音乐平台服务端架构设计，要求系统具有可扩展性， 能够支持大量并发用户；", "3、根据运营&产品需求，积极跟进业务功能与系统功能开发，并维护参数线上服务稳定与数据正常"], "requir": ["1、计算机软件或相关专业；", "2、熟悉java sdk提供的主要能力；熟悉多线程编程，熟练使用java并发包下的各项常用基础设施;", "3、熟悉网络编程，能够熟练使用java nio开发高并发、高吞吐量的服务;", "4、熟悉常用网络协议，如TCP/IP, HTTP;", "5、能够熟练使用linux，能够利用常用的工具对程序进行跟踪诊断;", "6、有分布式系统开发经验，对消息服务、负载均衡、高可用机制等有深入理解;", "7、具备良好学习、沟通能力及团队协作精神，对工作积极严谨，勇于承担压力。"]},
{"name": "高级Java开发工程师（曲库平台） - 音乐事业部002", "link": "https://hr.163.com/position/detail.do?id=20775", "address": "杭州市", "cotegory": "音乐事业部", "type": "技术>服务端开发", "num": "3人", "duty": ["1、负责音乐曲库平台服务端功能模块设计、开发、编码、测试以及文档编写等工作；", "2、负责音乐曲库平台服务端架构设计，要求系统具有可扩展性， 能够支持大量并发用户；", "3、根据运营&产品需求，积极跟进业务功能与系统功能开发，并维护参数线上服务稳定与数据正常", "4、优化系统性能，保证服务质量和稳定", "5、参与团队建设，辅导新同学成长"], "requir": ["1、计算机软件或相关专业；", "2、熟悉java sdk提供的主要能力， 熟悉常用Java技术栈通用框架、多线程编程，熟练使用java并发包下的各项常用基础设施;", "3、熟悉网络编程，能够熟练使用java nio开发高并发、高吞吐量的服务;", "4、熟悉常用网络协议，如TCP/IP, HTTP;", "5、能够熟练使用linux，能够利用常用的工具对程序进行跟踪诊断;", "6、有分布式系统开发经验，对消息服务、负载均衡、高可用机制等有深入理解;", "7、具备良好学习、沟通能力及团队协作精神，对工作积极严谨，勇于承担压力。", "8、对内容数据保持敏感性，有内容生产、管理、流程化处理设计经验的优先"]},
{"name": "有道数学线下渠道运营 - 有道事业群705", "link": "https://hr.163.com/position/detail.do?id=20810", "address": "北京市", "cotegory": null, "type": "市场>商务", "num": "1人", "duty": ["1. 开拓幼小市场线下渠道，如母婴店、早教机构等，推广在线教育课程。", "2. 持续寻找教育机构合作方，幼儿园、小学等，将在线数学课程推广至官方渠道。", "3. 结合项目自身优势资源和背景，进行线上和线下宣传，完成用户拉新和裂变。", "4. 能不断寻找、挖掘新的线上和线下合作方式，丰富业务推广渠道，促进项目发展。"], "requir": ["1. 熟悉互联网商务模式，有教育行业商务经验从业者优先。", "2. 两年以上的在线教育行业BD相关经验。", "3. 具有3-8岁宝妈类KOL、KOC、公众号资源者优先考虑。", "4. 适合出差者优先。"]},
{"name": "资深Java开发工程师（曲库平台） - 音乐事业部002", "link": "https://hr.163.com/position/detail.do?id=20774", "address": "杭州市", "cotegory": "音乐事业部", "type": "技术>服务端开发", "num": "2人", "duty": ["1、负责音乐曲库平台服务端功能模块设计、开发、编码、测试以及文档编写等工作；", "2、负责音乐曲库平台服务端架构设计，要求系统具有可扩展性， 能够支持大量并发用户；", "3、根据运营&产品需求，积极跟进业务功能与系统功能开发，并维护参数线上服务稳定与数据正常", "4、优化系统性能，保证服务质量和稳定", "5、参与团队建设，辅导新同学成长"], "requir": ["1、计算机软件或相关专业；", "2、熟悉java sdk提供的主要能力， 熟悉常用Java技术栈通用框架、多线程编程，熟练使用java并发包下的各项常用基础设施;", "3、熟悉网络编程，能够熟练使用java nio开发高并发、高吞吐量的服务;", "4、熟悉常用网络协议，如TCP/IP, HTTP;", "5、能够熟练使用linux，能够利用常用的工具对程序进行跟踪诊断;", "6、有分布式系统开发经验，对消息服务、负载均衡、高可用机制等有深入理解;", "7、具备良好学习、沟通能力及团队协作精神，对工作积极严谨，勇于承担压力。", "8、对内容数据保持敏感性，有内容生产、管理、流程化处理设计经验的优先"]},
{"name": "UE4美术设计师 - CC直播事业部300", "link": "https://hr.163.com/position/detail.do?id=20812", "address": "广州市", "cotegory": null, "type": "美术>设计类", "num": "5人", "duty": ["1.\t负责AR虚拟场景3D建模和修改，基于PBR流程制作贴图，熟悉材质系统和制作出符合视觉的材质，以及美术场景库整理和优化；", "2.\t运用引擎资源做整合场景，布置灯光以及烘焙灯光贴图，准确表达场景氛围；", "3.\t根据需求设计出粒子特效，角色特效，场景氛围特效，UI特效等；", "4.\t根据创意设计视频需求，把控动画影片的镜头和节奏，引擎渲染输出成片。"], "requir": ["1.\t优秀的场景物件塑造能力、气氛把控能力、布置灯光，材质制作，地形编辑制作，场景特效气氛；", "2.\t熟悉引擎动画系统、特效设计，包括镜头动画、定序器动画和蓝图驱动动画；", "3.\t熟知PBR流程，熟练运用Substance Painter绘制贴图；", "4.\t有良好的美感，了解分镜头、光线和色彩的运用；", "5.\t熟悉美术文件的优化整理和对接程序技术的优化。", "6.\t会C4D，了解AE，pr等后期制作软件。"]},
{"name": "杭州 - 产品策划专家-效率工程部", "link": "https://hr.163.com/position/detail.do?id=20816", "address": "杭州市", "cotegory": "互动娱乐事业群", "type": "策划>产品类", "num": "1人", "duty": ["1.负责云协作办公产品设计及优化，产品包括IM即时通讯、文档/知识管理工具、会议服务及OA办公工具等；", "2.负责开放平台建设，并推进各业务工具规范接入，打造服务闭环，建立一体化的协同工作平台；", "3.探索产品智能服务方式，推进产品智能化发展；", "4.把握行业发展方向，对标外部竞品，打造企业协同办公领域TOP产品。"], "requir": ["1.本科及以上学历，有6年以上B端产品策划经验，作为产品负责人统筹推进过大型B端产品并有成功产品经验；", "2.对企业协作办公产品有深入思考，了解行业发展趋势以及企业应用痛点，对工具类产品发展有较清晰的思考及规划；", "3.具备良好的用户调研和竞品分析方法论并有丰富实践经验，能够快速进入未知业务领域，并推进工具化解决策略；", "4.具备优秀的逻辑分析能力、沟通能力及跨部门协作推进能力；", "5.强成就动机，热爱工具型产品方向；", "6.富有激情，重视团队内部分享，持续学习，输出正能量；", "7.在企业协作办公领域有突出成就优先考虑。"]},
{"name": "UE4技术美术 - CC直播事业部300", "link": "https://hr.163.com/position/detail.do?id=20813", "address": "广州市", "cotegory": null, "type": "美术>游戏美术类", "num": "4人", "duty": ["1. 负责沟通协作解决美术方面的技术难题;", "2. 对接程序技术侧，优化文件修改BUG等问题;", "3. 熟悉并研究UE4引擎渲染架构，给予提升美术效果的技术支持，可帮助团队编写优化辅助工具的使用，如毛发插件，布料插件，材质渲染等;", "4. 熟练掌握UE4美术流程，能够快速搭建符合项目的场景;有C4D软件使用经验，会AE,PR后期软件", "5.\t对材质，灯光，3D动画，渲染有足够的理解，可独立通过蓝图制作相关内容。"], "requir": ["1. 有一定的美术认知，熟悉美术开发和PBR流程;", "2. 熟悉c/c++、unity3d、ue4等相关技术;", "3. 熟悉美术文件的优化整理和对接程序技术的优化;", "4. 良好的沟通能力和团队协作能力，需不断钻研软件功能，紧跟市场发展步伐。", "5. 有TA的相关工作经验。"]},
{"name": "资深3D场景制作设计师 - 逆水寒手游", "link": "https://hr.163.com/position/detail.do?id=19155", "address": "杭州市", "cotegory": null, "type": "游戏>游戏美术", "num": "6人", "duty": ["1、擅长次时代武侠写实风格、标准PBR流程的3D制作；", "2、积累和共享场景制作/场景编辑经验，分享设计经验。；", "3、需要保持与策划，设计，技术等相关部门保持紧密的合作与沟通，提升项目的美术品质及优化现有工作流程； ", "4、根据游戏设定，理解原画意图，制作3D场景模型以及物件资源、贴图绘制和材质制作； ", "5、理解游戏的美术风格和质量跟进，进行整流程环节配合，完成产品的美术效果实现； ", "6、对研发流程和环节配合有较高的敏感性和认知度，对自身岗位的上下游岗位有清楚的了解；"], "requir": ["1、 具有较强的美术背景，大专（全日制）以上学历； ", "2、 具备熟练的建模能力、有坚实的绘画技巧和良好的色彩感；  ", "3、 熟练操作掌握3dmax/Maya，Zbrush/Mudbox，Substance Designer/Painter, Quixel suit, Marvelous Designer,Photoshop等其他相关制作软件； ", "4、对Unity3d引擎工作有一定游戏制作经验者优先，有武侠手游制作经验优先；", "5、具备丰富的制作次世代游戏经验，熟练运用PBR标准流程进行制作，擅长speedtree植物制作流程者优先；", "6、具有较强责任感及良好的沟通技巧，有较强的团队意识 ，对新技术有敏锐的嗅觉，学习能力强；", "7、对于游戏开发充满激情，做事积极主动；"]},
{"name": "培训实习生-乐读-有道事业群702 - 有道事业群705", "link": "https://hr.163.com/position/detail.do?id=20817", "address": "杭州市", "cotegory": null, "type": "教育>教育", "num": "1人", "duty": ["1.负责新人培训的运营工作，包括上课安排 通知 签到、培训作业 收集 批改 反馈等。", "2.协同培训师完成日常培训工作", "3.共同探讨并辅助完善现有的培训，使培训结果不断精进和完善。"], "requir": ["1. 本科及以上学历，大三、研一研二优先考虑，有在线教育工作经验优先", "2.熟练使用word、excel、ppt等办公软件", "3.吃苦耐劳，有责任心，对待琐碎的事情能够踏实认真去做，并且高质量完成", "4.对培训产品有属于自己的见解和看法"]},
{"name": "广州_资深美术项目管理工程师 - 项目管理中心611", "link": "https://hr.163.com/position/detail.do?id=20815", "address": "广州市", "cotegory": null, "type": "技术>其他", "num": "1人", "duty": ["1. 负责游戏项目开发（美术方向）的内外部管理工作，组织并执行从需求、计划、制作、审核，验收到结算的整个过程；", "2. 负责制定游戏开发需求规划和详细计划，跟进执行推动项目进展，并定期总结；", "3. 负责对内外部的开发制作进度，成本，质量的沟通和管理；", "4. 参与支持公司层面供应商管理的工作；", "5. 协助职能经理做好团队管理工作；", "6. 负责接口其他相关部门工作，并合理安排档期；"], "requir": ["1. 热爱美术，有美术、设计相关专业学习背景或从事过关美术、设计相关工作，审美良好；", "2. 大学本科及以上学历，有3年以上项目管理经验；", "3. 熟悉项目管理技能，包括项目总体规划，项目估算及计划，项目状态监控及控制，风险管理，变更管理，项目总体状态报告（周/月/季度）；熟悉敏捷项目管理更佳；", "4. 良好的沟通协作力，较强的抗压力，出色的团队合作精神；", "5. 积极上进，具备自我激励、团队精神、责任心；", "6. 拥有 PMP 证书或Scrum Master 认证优先；", "7.热爱游戏，游戏经验丰富者更佳；"]},
{"name": "IT工程师 - 运营中心140", "link": "https://hr.163.com/position/detail.do?id=20814", "address": "广州市", "cotegory": null, "type": "运营>运营类", "num": "3人", "duty": ["1、桌面，网络和服务器等设备故障诊断，解决相关问题；", "2、负责视频会议系统，电话系统，邮件系统等的管理", "3、管理维护公司网络设备，维护公司内部服务器；", "4、负责员工桌面级IT支持工作；", "5、上级交办的其它工作任务，做好工作汇报。"], "requir": ["1、大专及以上学历，计算机等相关专业；", "2、熟悉网络设备，有实操经验，包括不限于（cisco,H3C）交换机，路由器,无线ap部署和调试；", "3、有helpdesk项目经验，熟悉日常办公设备和电脑软件的故障检测及排除，给vip提供优质服务；", "4、熟悉主流操作系统，有AD域相关系统部署和调试优化优先； ", "5、扎实的计算机专业基础，有开发经验，包括不限于脚本批量部署，自动化运维系统搭建维护优先；", "6、具有良好的语言表达能力和沟通技巧，工作积极主动，具备较强的责任感。"]},
{"name": "广州_高级/资深研发PM - 项目管理中心500", "link": "https://hr.163.com/position/detail.do?id=18915", "address": "广州市", "cotegory": null, "type": "技术>其他", "num": "2人", "duty": ["协助产品制作人进行大型在线游戏或手机游戏研发的日常项目管理工作，参与产品研发的整个生命周期，包括项目预研、项目启动、项目计划、项目执行和控制等各个阶段。具体如下： ", "1. 协助主管制定项目的计划和时间表； ", "2. 负责推动团队日常执行工作，负责进度跟踪和控制，确保工作按计划完成； ", "3. 负责团队内部敏捷项目管理流程和工具的执行，并从项目管理的观点和角度对团队内部流程进行推进和优化； ", "4. 建立清晰、透明和高效的沟通机制，收集和准备项目管理状态报告；"], "requir": ["1. 热爱游戏； ", "2. 大学本科以上学历，计算机、软件工程等相关专业， 3年以上软件研发相关工作经验； ", "3. 独立负责过软件研发项目的项目管理工作； ", "4. 熟悉项目管理知识体系、软件工程和软件质量控制，深入了解研发项目的特点； ", "5. 熟悉敏捷项目管理，具有较为规范的项目管理实战技能； ", "6. 具有良好的沟通、协调和团队领导能力； ", "7. 拥有PMP证书或Scrum Master认证优先,有海外工作和学习背景者优先。"]},
